{
    "data":
    [
        {
            "seq": "100",
            "type": "LB05",
            "name": "제주 선조들의 교훈",
            "siteName": "제주 선조들의 교훈",
            "contents": "우리 제주도 하르방들이 호는 말이 있수다.\n\n밭을 살 땐 에염을 보라.\n집을 살 땐 이웃을 보라.\n산을 사컨 빌레를 보라.\n사돈을 홀 땐 근본(뿌리)을 보라.\n그리고 우리 어멍들이 고르친 말이 있수다.\n\n홈생이 말라. 촐람생이질 말라.\n간세 말라. 느링테질 말라.\n요망진 체 말라. 거들락 거리지 말라.\n노미 모심 아프게 호지 말라.\n경해사 호는 일들이 펜안해 진다.\n\n살당 보민 잊어 불 때도 있수다만\n우리 하르방, 할망, 아방, 어멍들이\n혼 말씀들은 촘말로 소중한 교훈들이우다.",
            "original": "우리 제주도 하르방들이 &#62775;는 말이 잇수다.\n\n밧을 살 땐 에염을 보라.\n집을 살 땐 이웃을 보라.\n산을 사컨 빌레를 보라.\n사돈을 &#62780; 땐 근본(뿌리)을 보라.\n그리고 우리 어멍들이 &#57767;르친 말이 잇수다.\n\n&#62789;생이 말라. 촐람생이질 말라.\n간세 말라. 느렁테질 말라.\n요망진 체 말라. 거들락거리지 말라.\n&#58000;의 &#58720;심 아프게 &#62775;지 말라.\n경헤사 &#62775;는 일들이 펜안헤 진다.\n\n살당 보민 잊어 불 때도 잇수다만\n우리 하르방, 할망, 아방, 어멍들이\n&#62778; 말씀들은 &#62283;말로 소중한 교훈들이우다.",
            "solution": "우리 제주도 할아버지들이 하시는 말씀이 있습니다.\n\n밭을 살 때는 밭 옆을 보고 사라.\n집을 살 때는 이웃들을 보고 사라.\n산을 사려면 돌(암반)을 보고 사라.\n사돈을 맺을 때는 집안의 뿌리를 보고하라.\n그리고 우리 어머니들이 가르친 말씀이 있습니다.\n\n어리광 부리지 말라. 경솔하게 나서지 말라.\n게으르지 말라. 느림보가 되지 말라.\n꾀부리며 잘난 척 말라. 거만하지 말라.\n남의 마음 아프게 하지 말라.\n그래야 하는 일들이 편안히 잘된다.\n\n살다 보면 잊어버릴 대가 있습니다만\n우리 할아버지, 할머니, 아버지, 어머니들이\n하신 말씀들은 정말로 소중한 교훈들입니다.",
            "soundUrl": "/media/wiH",
            "image1Url": "/media/wyZ",
            "category": "ADMIN",
            "count": "7244"
        },
        {
            "seq": "99",
            "type": "LB01",
            "name": "사랑하는 비바리에게",
            "siteName": "사랑하는 처녀에게",
            "contents": "물 허벅 정 가는 저 비바리야!\n물만 지지 말앙, 이 소나이 모심도 정 가도라.\n\n소랑 혼댄 말은 못하곡,\n돌고망에 고분 생이고치, 가슴만 톨랑 톨랑!\n\n어떵 호민 조코 마씀!\n멍는거나 고트민 맨도롱 혼 때\n호로록 들여싸 불기나 혼다.\n물이나 되시민 허벅 속으로 퐁당 들어가기나 혼다.\n\n영도 못하곡, 정도 못하곡,\n비바리야, 촘말로 죽어 지키여!\n소나이 타는 모심을 호꼼 만이라도 알아도라.",
            "original": "물 허벅 정 가는 저 비바리야!\n물만 지지 말앙, 이 &#59773;나이 &#58720;심도 정 가&#58250;라.\n\n&#59773;랑 &#62778;덴 말은 못허곡,\n돌고망에 곱은 생이&#57767;치, 가슴만 &#62528;랑 &#62528;랑!\n\n어떵&#62775;민 좋고마씀!\n먹는거나 &#57767;트민 멘도롱&#62778; 때\n호로록 들여싸 불기나 &#62778;다.\n물이나 뒈시민 허벅 속으로 퐁당 들어가기나 &#62778;다.\n\n영도 못허곡, 정도 못허곡,\n비바리야, &#62283;말로 죽어지키여!\n&#59773;나이 타는 &#58720;심을 &#62775;꼼만이라도 알아&#58250;라.",
            "solution": "물동이 지고 가는 저 처녀야!\n물만 지고 가지 말고 이 총각의 마음도 지고 가다오\n\n사랑한다고 말은 못하고\n돌틈(돌구멍)에 숨은 새 같이 가슴만 철렁 철렁\n\n어떻게 하면 좋겠습니까요?\n먹을 수 있는 것이라면 따뜻할 때\n후루룩 마셔 버리기나 한다\n물이나 된다면 물동이 속으로 풍덩 들어 가기나 한다.\n\n이렇게도 못하고, 저렇게도 못하고,\n처녀야! 참말로 죽겠다.\n총각이 타는 마음을 조금 만이라도 알아다오.",
            "soundUrl": "/media/wiG",
            "image1Url": "/media/wyL",
            "category": "ADMIN",
            "count": "5335"
        },
        {
            "seq": "98",
            "type": "LB03",
            "name": "갑돌이와 갑순이 이야기",
            "siteName": "갑돌이와 갑순이 이야기",
            "contents": "어느 모실에 갑돌이옌 호는 소나이와,\n갑순이옌 호는 비바리가 살았수게.\n둘이는 좋아 하멍도 말은 못하곡,\n속은 타멍도 그 까짓거 해여십주.\n\n경 호단, 갑순이가 씨집가게 되난,\n그제사 갑돌이가 `아이구! 어멍아!` 하멍 울었수게.\n경 해도 어떵 해여 마씀, 홀수가 어서십주.\n갑돌이도 부에가 난, 장게를 가 부렀수게.\n\n장게 가는 날은 갑순이도 정지에서 울었수게.\n갑순이 모심도 갑돌이 뿐이주만 어떵 홉니까?\n\n사롬 팔재 촘, 몰르능거라 마씀.\n게난, 어떵 살코? 저들멍 살지 맙서.\n살당 보민, 타고난 팔재대로 다 살아 짐니다.",
            "original": "어느 &#58720;실에 갑돌이옌 &#62775;는 &#59773;나이와\n갑순이옌 &#62775;는 비바리가 살앗수게.\n둘이는 좋아&#62775;멍도 말은 못&#62775;곡,\n속은 타멍도 그 까짓 거 헤여십주.\n\n경&#62775;단, 갑순이가 씨집가게 뒈난\n그제사 갑돌이가 `아이구! 어멍아!` 허멍 울엇수게.\n경헤도 어떵헤여마씀 &#62780; 수가 어서십주.\n갑돌이도 부에가 난, 장게를 가부럿수게.\n\n장게가는 날은 갑순이도 정지에서 울엇수게.\n갑순이 &#58720;심도 갑돌이 뿐이주만 어떵&#62790;니까?\n\n사롬 팔재 &#62283;, 몰르는거라마씀.\n게난 어떵살코? 저들멍 살지 맙서.\n살당 보민 타고난 팔재대로 다 살아집니다.",
            "solution": "어느 마을에 갑돌이라고 하는 사나이(총각) 와\n갑순이라고 하는 처녀가 살았습니다.\n두 사람은 좋아 하면서도 말은 못하고\n속으로는 타면서도 그 까짓거 하였답니다.\n\n그렇게 하다가 갑순이가 시집을 가게 되니까\n그때야 갑돌이가 `아이구! 어머니!` 하면서 울었습니다.\n그렇게 하더라도 어떻게 합니까? 할 수가 없었습니다.\n\n갑돌이도 화가 나서 장가를 가 버렸습니다.\n장가가는 날은 갑순이도 부엌에서 울었습니다.\n갑순이 마음도 갑돌이 뿐이었습니다만 어찌 합니까?\n\n사람 팔자는 참으로 모르는 것입니다.\n그러니 어떻게 살까? 걱정하면서 살지 마십시오.\n살다 보면 타고난 운명대로 다 살기 마련입니다.",
            "soundUrl": "/media/wiF",
            "image1Url": "/media/wyK",
            "category": "ADMIN",
            "count": "5687"
        },
        {
            "seq": "97",
            "type": "LB07",
            "name": "새각씨 구호는 법",
            "siteName": "새각씨 구하는 법",
            "contents": "새각씨 구홀 때랑 모심을 보라.\n얼굴 곱들락 혼 것은 혼 덜이여!\n놀씬호곡 멋진 것은 혼 해여!\n모심 착한 건, 십 년이 되곡 백 년이 되도\n저 소낭 추룩 청청혼다.",
            "original": "새각씨 구&#62780; 때랑 &#58720;심을 보라.\n얼굴 곱들락&#62778; 것은 &#62778; &#58255;이여!\n&#57992;씬&#62775;곡 멋진 것은 &#62778; 해여!\n&#58720;심 착한 건 십 년이 뒈곡 백 년이 뒈도\n저 소낭추룩 청청&#62778;다.",
            "solution": "색시 구할 때는 마음을 봐라.\n얼굴 고운 것은 한 달이여!\n날씬하고 멋진 것은 일 년이야!\n마음 착한 건, 십 년이 되고 백 년이 되도\n저 소나무 처럼 청청하다.",
            "soundUrl": "/media/wiD",
            "image1Url": "/media/wyJ",
            "category": "ADMIN",
            "count": "3904"
        },
        {
            "seq": "96",
            "type": "LB03",
            "name": "제주도 사투리 높이는 말과 낮추는 말",
            "siteName": "제주도 사투리 높이는 말과 낮추는 말",
            "contents": "혼저 옵서게 ……………… 혼저 오라게\n고만 십서게 ……………… 고만 시라게\n무신 거 햄쑤과? ……………… 무신 거 햄시니?\n무사 경 급호꽈? ……………… 무사 경 급호냐?\n게메 마씸, 확 옵서게 …………… 기여 게, 확 오라게",
            "original": "&#62778;저 옵서게 ………………&#62778;저 오라게\n&#57767;만 십서게 ………………&#57767;만 시라게\n무신 거 헴수과? ……………… 무신 거 헴시니?\n무사 경 급허우과? ……………… 무사 경 급허니?\n게메마씸, 확 옵서게. …………… 기여게 확 오라게.",
            "solution": "어서 오십시오 어서 오너라\n잠깐 있으십시오 잠깐 있어라\n무엇을 하십니까? 무엇을 하느냐?\n왜 그렇게 급하십니까? 왜 그렇게 급하냐?\n그래요, 빨리 오십시오 그래, 빨리 오너라",
            "soundUrl": "/media/wiS",
            "image1Url": "/media/wyH",
            "category": "ADMIN",
            "count": "8813"
        },
        {
            "seq": "95",
            "type": "LB06",
            "name": "촘앙 삽서",
            "siteName": "참으면서 사십시오",
            "contents": "어떵 살코 마씸?\n무사 경 저들멍 살암쑤과?\n촘앙 삽서.\n경 햄시민 살아짐니다.",
            "original": "어떵 살코마씸?\n무사 경 저들멍 살암수과?\n&#62283;앙 삽서.\n경 헴시민 살아집니다.",
            "solution": "어떻게 살면 되겠습니까?(걱정하는 소리)\n왜 그렇게 걱정하면서 사십니까?\n참으면서 사십시오.\n그러다 보면 살아 갈 수 있습니다.\n(※마씸 = 마씀)",
            "soundUrl": "/media/wiA",
            "image1Url": "/media/wyG",
            "category": "ADMIN",
            "count": "5237"
        },
        {
            "seq": "94",
            "type": "LB04",
            "name": "제주 바당 노래(민요에서)",
            "siteName": "제주 바다 노래(민요에서)",
            "contents": "우이 어멍 사는 바당, 우리 목숨 키운 바당\n동에 가민 동의 바당, 서에 가민 서의 바당\n보름 불민 파도 치곡, 비가 오민 날 저물곡\n하늘 고튼 요왕님아, 명주 바당 맨들어서\n우리 어멍 설은 가슴, 펭안호게 호여 줍서.",
            "original": "우리 어멍 사는 바당 우리 목숨 키운 바당\n동에 가민 동의 바당, 서에 가민 서의 바당\n&#58954;름 불민 파도 치곡, 비가 오민 날 저물곡\n하늘 &#57767;튼 요왕님아, 명주 바당 멘들어서\n우리 어멍 설운 가슴, 펜안&#62775;게 &#62775;여줍서.",
            "solution": "우리 어머니 사는 바다, 우리 목숨을 키운 바다\n동쪽으로 가면 동의 바다, 서쪽으로 가면 서의 바다\n바람이 불면 파도가 치고, 비가 오면 날이 저물고\n하늘같은 용왕님이여, 명주실같이 잔잔한 바다 만들어서\n우리 어머니 서러운 가슴, 편안하게 하여 주소서.",
            "soundUrl": "/media/wiP",
            "image1Url": "/media/wyF",
            "category": "ADMIN",
            "count": "2943"
        },
        {
            "seq": "93",
            "type": "LB05",
            "name": "호꼼만 촘앙 살암시라",
            "siteName": "조금만 참고 살고 있어다오",
            "contents": "촘말로 가쿠과?\n게메, 홀수가 엇다게.\n게민, 나 혼자만 어떵 살랜 마씀?\n어떵 호느니, 호꼼만 촘앙 살암시라.\n떠나는 내 모심도 울어 지키여.",
            "original": "&#62283;말로 가쿠과?\n게메 &#62780;수가 엇다게.\n게민, 나 혼자만 어떵살렌마씀?\n어떵&#62775;느니, &#62775;꼼만 &#62283;앙 살암시라.\n떠나는 내 &#58720;심도 울어지키여.",
            "solution": "정말로 가시겠습니까?\n글세, 어쩔수가 없단다.\n그럼, 나 혼자만 어떻게 살라고 하십니까?\n어쩔 수 없지 않느냐, 조금만 참고 살고 있어다오.\n떠나는 내 마음도 울고 싶단다.",
            "soundUrl": "/media/wiO",
            "image1Url": "/media/wyD",
            "category": "ADMIN",
            "count": "2717"
        },
        {
            "seq": "92",
            "type": "LB05",
            "name": "소랑이나 호게 마씀",
            "siteName": "사랑이나 합시다요",
            "contents": "어드레 감쑤과?\n이래 옵서게.\n혼저 혼저 옵서게.\n솔짝 솔짝 옵서게.\n느영 나영, 두리 둥실 소랑이나 호게 마씀.",
            "original": "어드레 감수과?\n이레 옵서게.\n&#62778;저 &#62778;저 옵서게.\n&#59778;짝 &#59778;짝 옵서게.\n느영 나영, 두리둥실 &#59773;랑이나 &#62775;게 마씀.",
            "solution": "어디로 가십니까?\n이리로 오십시오.\n어서 어서 오십시오.\n살짝 살짝 오십시오.\n너랑 나랑, 둘이 둥실 사랑이나 합시다요.",
            "soundUrl": "/media/wiI",
            "image1Url": "/media/wyS",
            "category": "ADMIN",
            "count": "3325"
        },
        {
            "seq": "91",
            "type": "LB05",
            "name": "제주도 사투리 인사들",
            "siteName": "제주도 사투리 인사들",
            "contents": "누게 있수과? (사롬 있수과?)\n안녕 하우꽈?\n아방, 어멍 다 펜안 했수과?\n어디 갔당 왐쑤과?\n요새 어떵 살미꽈? 좋수과?",
            "original": "누게 잇수과? (사롬 있수과?)\n안녕허우과?\n아방 어멍 다 펜안헷수과?\n어디갓당 왐수과?\n요새 어떵살미우과? 좋수과?",
            "solution": "누구 있습니까?\n안녕 하십니까?\n아버지, 어머니 모두 편안 하셨습니까?\n어디 갔다가 오십니까?\n요새 어떻게 사십니까? 좋습니까?",
            "soundUrl": "/media/wiU",
            "image1Url": "/media/wyA",
            "category": "ADMIN",
            "count": "18498"
        },
        {
            "seq": "90",
            "type": "LB06",
            "name": "무싱 거옌 고릅디가?",
            "siteName": "뭐라고 말하던가요?",
            "contents": "무사, 무싱 거옌 고릅디가?\n솔째기 왕 말홉서, 보저.\n게메, 말호카, 말카?\n속 태우지 말앙 확 홉서게.\n게민, 놈 혼테랑 아무 말도 호지 맙서, 양?",
            "original": "무사, 무싱 거옌 &#57773;읍디가?\n&#59778;째기 왕 말&#62790;서, 들어보저.\n게메, 말호카 말카?\n속 태우지 말앙 확 &#62790;서게.\n게민 &#58000; 안티랑 아무 말도 &#62775;지 맙서양?",
            "solution": "왜, 뭐라고 말하던가요?\n살짝 와서 말하십시오. 들어 봅시다.\n글쎄, 말할까, 말까?\n속 태우지 말고 빨리 하십시오.\n그럼, 남 한테는 아무 말도 하지 마십시오, 네?",
            "soundUrl": "/media/wiY",
            "image1Url": "/media/wyP",
            "category": "ADMIN",
            "count": "4505"
        },
        {
            "seq": "89",
            "type": "LB06",
            "name": "날 도랑 가 줍서",
            "siteName": "나를 데리고 가 주십시오",
            "contents": "서울엔 언제 가쿠과?\n갈 때랑 날 도랑 가 줍서.\n서울 강 무싱 거 호젠?\n구경도 호곡, 서울 소랑도 해 보젠 마씀.",
            "original": "서울엔 언제 가쿠과?\n갈 때랑 날 &#58250;랑 가 줍서.\n서울 강 무싱 거 &#62775;젠?\n구경도 &#62775;곡, 서울 &#59773;랑도 헤보젠마씀.",
            "solution": "서울에는 언제 가겠습니까?\n갈 때는 나를 데리고 가 주십시오.\n서울 가서 무엇을 하려고?\n구경도 하고, 서울 사랑도 해 보려고요.",
            "soundUrl": "/media/wiT",
            "image1Url": "/media/wyO",
            "category": "ADMIN",
            "count": "2339"
        },
        {
            "seq": "88",
            "type": "LB01",
            "name": "귀 눈이 왁왁해라",
            "siteName": "눈앞이 캄캄하니 정신이 없더라",
            "contents": "씨집가난 어떵 홉디가?\n아이고, 말도 말라.\n무신 거시 무신 건지,\n귀 눈이 왁왁해라.",
            "original": "씨집가난 어떵&#62790;디가?\n아이고, 말도 말라.\n무신 것이 무신 건지,\n귀 눈이 왁왁해라.",
            "solution": "시집가니까 어땠습니까?\n아이고, 말도 마라.\n뭐가 뭔지,\n눈앞이 캄캄하니 정신이 없더라.\n(※귀눈이 왁왁 : 귀와 눈이 막혀 캄캄한 모습)",
            "soundUrl": "/media/wiR",
            "image1Url": "/media/wyI",
            "category": "ADMIN",
            "count": "2261"
        },
        {
            "seq": "87",
            "type": "LB05",
            "name": "어떵 살아 점쑤과?",
            "siteName": "어떻게 살고 있습니까?",
            "contents": "어느제 옵디가?\n혼 사나흘 됐수다.\n다들 펜안 했수과?\n어떵 살아 점쑤과?",
            "original": "어느제 옵디가?\n&#62778; 사나흘 &#46235;수다.\n다들 펜안헷수과?\n어떵 살아점수과?",
            "solution": "언제 오셨습니까?\n한 사나흘 되었습니다.\n모두 편안 했습니까?\n어떻게 살고 있습니까?\n(※오랜만에 서로 만나 인사하는 말들)",
            "soundUrl": "/media/wiE",
            "image1Url": "/media/wyU",
            "category": "ADMIN",
            "count": "2354"
        },
        {
            "seq": "86",
            "type": "LB01",
            "name": "나 모심 몰르쿠과?",
            "siteName": "제 마음 모르겠습니까?",
            "contents": "나 모심 몰르쿠과?\n당신만 보민 가슴이 금착 금착\n영도 못하곡, 정도 못하곡,\n나 모심, 나도 몰르쿠다.",
            "original": "나 &#58720;심 몰르쿠과?\n당신만 보민 가슴이 금착금착\n영도 못허곡 정도 못허곡,\n나 &#58720;심, 나도 몰르쿠다.",
            "solution": "제 마음 모르겠습니까?\n당신만 보면 가슴이 두근 두근\n이러지도 못하고, 저러지도 못하고,\n제 마음, 저도 모르겠습니다.\n(※사랑하는 마음을 말함)",
            "soundUrl": "/media/wiW",
            "image1Url": "/media/wyY",
            "category": "ADMIN",
            "count": "2324"
        },
        {
            "seq": "85",
            "type": "LB06",
            "name": "똥 뀐 놈이 성 냄쩌",
            "siteName": "방귀 뀐 놈이 화 내고 있네",
            "contents": "무신 걸 잘 하구랜 큰 소리꽈?\n똥 뀐 놈이 성 냄쩌.\n누겐 입 어선 말 못 햄시카 부댄?\n지랭이도 볼부민 꿈틀락홉니다, 양!",
            "original": "무신 걸 잘 허구렌 큰 소리우과?\n똥뀐 놈이 성 냄저.\n누겐 입 어선 말 못 헴시카부덴?\n지렝이도 &#58959;부민 꿈틀락&#62790;니다양!",
            "solution": "무엇을 잘 했다고 큰 소리입니까?\n방귀 뀐 놈이 화 내고 있네.\n누가 입이 없어서 말을 못 하는줄 아는가?\n지렁이도 밟으면 꿈틀거립니다, 예!\n(※양 : 강조할때 쓰는 말)",
            "soundUrl": "/media/wiQ",
            "image1Url": "/media/wyT",
            "category": "ADMIN",
            "count": "2164"
        },
        {
            "seq": "84",
            "type": "LB01",
            "name": "잘 돌앙 살아 줍서",
            "siteName": "잘 데리고 살아 주십시오",
            "contents": "우리 똘은 아무것도 몰라 마씸.\n분시 몰른 애기, 설운 애기 우다.\n잘 돌앙 살아 줍서\n고르치멍 살아사 할 꺼우다.",
            "original": "우리 &#58344;은 아무 것도 몰라마씸.\n분시 몰른 애기 설운 애기우다.\n잘 &#58255;앙 살아줍서\n&#57767;르치멍 살아사 헐 거우다.",
            "solution": "우리 딸은 아무것도 모릅니다.\n세상 물정 잘 모르는 아이, 어린 아이입니다.\n잘 데리고 살아 주십시오.\n가르치면서 살아야 할 겁니다.",
            "soundUrl": "/media/wim",
            "image1Url": "/media/wyR",
            "category": "ADMIN",
            "count": "2228"
        },
        {
            "seq": "83",
            "type": "LB05",
            "name": "사롬 있수과?",
            "siteName": "사람 있습니까?(안녕 하십니까?)",
            "contents": "사롬 있수과?\n누게꽈?\n웃 동네 갑돌이 어멍 이우다.\n아이구, 어떵 호난 와 집디가 게?",
            "original": "사롬 잇수과?\n누게과?\n웃동네 갑돌이 어멍이우다.\n아이구 어떵 &#62775;난 와집디가게?",
            "solution": "사람 있습니까?(안녕 하십니까?)\n누구십니까?\n윗 동네 갑돌이 어머니 입니다.\n아이구, 어떻게 해서 왔습니까?\n(※사롬 있수과 : 남의 집 방문시의 인사)",
            "soundUrl": "/media/win",
            "image1Url": "/media/wyE",
            "category": "ADMIN",
            "count": "2468"
        },
        {
            "seq": "82",
            "type": "LB06",
            "name": "숨 고끼키여!",
            "siteName": "숨 넘어간다",
            "contents": "호꼼씩 먹으라. 숨 넘어가키여.\n배 고판 마씀.\n경 먹당은 숨 고끼키여!\n누게 도둑질 안하메 촌촌히 먹으라.",
            "original": "&#62775;꼼씩 먹으라. 숨 넘어가키여.\n배 고판마씀.\n경 먹당은 숨 &#57767;끼키여!\n누게 도둑질 안헌니 &#62275;&#62275;히 먹으라.",
            "solution": "조금씩 먹어라. 숨 넘어간다.\n배 고파서 말입니다.\n그렇게 먹다간 숨이 막히겠다!\n누가 훔쳐 가지 않으니 천천히 먹어라.",
            "soundUrl": "/media/wib",
            "image1Url": "/media/wyW",
            "category": "ADMIN",
            "count": "1931"
        },
        {
            "seq": "81",
            "type": "LB06",
            "name": "뚜러메당 데껴 불키여",
            "siteName": "들러메어 던져 버리겠어",
            "contents": "말도 안 득곡, 일도 안 호곡,\n촘말로, 경 호민\n뚜러메당 데껴 불키여.\n사롬은 일해사 살아 지는거여!",
            "original": "말도 안 듣곡, 일도 안 &#62775;곡,\n&#62283;말로 경&#62775;민\n뚜러메당 데껴 불키여.\n사롬은 일헤사 살아지는 거여!",
            "solution": "말도 안 듣고, 일도 안 하고,\n정말, 그렇게 하면\n들러메어 던져 버리겠어.\n사람은 일을 해야 살 수 있는 거야!",
            "soundUrl": "/media/wiv",
            "image1Url": "/media/wyQ",
            "category": "ADMIN",
            "count": "4171"
        },
        {
            "seq": "80",
            "type": "LB01",
            "name": "저리 고쩌 사불라",
            "siteName": "저리로 비켜 서라",
            "contents": "새서방 들어 왐쩌.\n저리 고쩌 사불라\n영 홉서. 호꼼만 보게마씀!\n몰치락 혼게, 잘도 생겼저.",
            "original": "새시방 들어 왐저.\n저리 고쩌사불라\n영 &#62790;서. &#62775;꼼만 보게마씀!\n몰치락 &#62778;게, 잘도 생겻저.",
            "solution": "새신랑 들어 온다.\n저리로 비켜 서라.\n이렇게 하십시오. 조금만 봅시다!\n알맞게 살찐 모습이, 잘 생겼구나.",
            "soundUrl": "/media/wic",
            "image1Url": "/media/wym",
            "category": "ADMIN",
            "count": "1266"
        },
        {
            "seq": "79",
            "type": "LB04",
            "name": "이어도 사나 민요",
            "siteName": "이어도 사나 민요",
            "contents": "널븐 바당 앞을 재여, 혼질 두질 나아가곡\n짚은 바당 짚일 재여, 혼질 두질 들어가민\n저승길이 왔닥 갔닥, 이어도 사나, 이어도 사나,\n이어도가 저승질이 반이옌 혼다.",
            "original": "널븐 바당 앞을 재여, &#62778;질 두질 나아가곡\n지픈 바당 지피 재여, &#62778;질 두질 들어가민\n저승길이 왓닥갓닥 이어도 사나 이어도 사나,\n이여도가 저승질이 반이옌 혼다.",
            "solution": "넓은 바다 앞을 재면서, 한 길 두 길 앞으로 가고\n깊은 바다 깊이를 재며, 한 길 두 길 들어가면\n저승길이 오락 가락, 이어도 사나, 이어도 사나,\n이어도(섬)가 저승길의 반이라 한다.\n(※이어도 : 제주도 해녀들이 생각하는 상상의 섬)",
            "soundUrl": "/media/wix",
            "image1Url": "/media/wyn",
            "category": "ADMIN",
            "count": "1990"
        },
        {
            "seq": "78",
            "type": "LB04",
            "name": "느영, 나영, 둘이 둥실",
            "siteName": "너하고 나하고 두 사람이 둥실(새타령)",
            "contents": "느영, 나영, 둘이 둥실\n낮에 낮이나, 밤에 밤이나 쌍소랑 이로구나.\n아척에 우는 생인, 배가 고팡 울고요\n조녁에 우는 생인, 님 그리웡 운다.",
            "original": "느영 나영 두리 둥실\n낮에 낮이나, 밤에 밤이나 상&#59773;랑이로구나.\n아척에 우는 셍인 배가 고팡 울고요\n&#61948;녁에 우는 셍인 님 그리왕 운다.",
            "solution": "너하고 나하고 두 사람이 둥실\n낮에 낮이나, 밤에 밤이나, 서로 사랑 이로구나.\n아침에 우는 새는, 배가 고파 울고요\n저녁에 우는 새는, 님 그리워서 운다.",
            "soundUrl": "/media/wiz",
            "image1Url": "/media/wyb",
            "category": "ADMIN",
            "count": "1742"
        },
        {
            "seq": "77",
            "type": "LB07",
            "name": "멍텅혼 사롬",
            "siteName": "멍청한 사람",
            "contents": "괴기, 멍텅혼 건 잡아나 먹곡\n낭, 멍텅혼 건 불이나 솜곡\n돌, 멍텅혼 건 담이나 닷나.\n사롬, 멍텅혼 건 아무 것에도 못 쓰키여!",
            "original": "궤기 멍텅&#62778; 건 잡아나 먹곡\n낭 멍텅&#62778; 건 불이나 &#59787;곡\n돌, 멍텅&#62778; 건 담이나 닿나.\n사롬 멍텅&#62778; 건 아무 것에도 못 쓰키여!",
            "solution": "고기, 멍청한 것은 잡아나 먹고\n나무, 멍청한 것은 불이나 때고\n돌, 멍청한 것은 담이나 쌓는다.\n사람, 멍청한 것은 아무 것에도 못 쓰겠구나!",
            "soundUrl": "/media/wil",
            "image1Url": "/media/wyv",
            "category": "ADMIN",
            "count": "1182"
        },
        {
            "seq": "76",
            "type": "LB03",
            "name": "돌 고냥",
            "siteName": "돌 구멍",
            "contents": "돌 고냥으로 보라.\n꽃들이 모들락 호게 피어 있저.\n우리 님의 얼굴도, 꽃치 되언 피엄쩌.\n소랑 소랑 소랑꽃도 고득호게 피엄쩌",
            "original": "돌 &#57767;냥으로 보라.\n꼿들이 모들락&#62775;게 피어 잇저.\n우리 님의 얼굴도, 꼿이 뒈언 피엄저.\n&#59773;랑 &#59773;랑&#59773;랑꼿도 &#57767;득&#62775;게 피엄저.",
            "solution": "돌 구멍으로 보아라.\n꽃들이 모두 모여서 피어 있구나.\n우리 님의 얼굴도, 꽃이 되어 피고 있구나.\n사랑 사랑 사랑꽃도 가득하게 피고 있구나.",
            "soundUrl": "/media/wik",
            "image1Url": "/media/wyc",
            "category": "ADMIN",
            "count": "1115"
        },
        {
            "seq": "75",
            "type": "LB04",
            "name": "도새기 타령",
            "siteName": "돼지 타령",
            "contents": "돌아 맨 도새기야! 니 신세가 불쌍호다.\n아이구, 기시린 도새기야! 나 걱정 말앙\n니 죽어 가능 거나 걱정호라.\n죽어 가능 게 벨것 다 걱정햄시니?",
            "original": "&#58255;아 맨 도새기야! 니 신세가 불쌍&#62775;다.\n아이구, 기시린 도새기야! 나 걱정 말앙\n니 죽어 가는 거나 걱정&#62775;라.\n죽어 가는 게 벨것 다 걱정헴시니?",
            "solution": "달아 맨 돼지야! 너의 신세가 불쌍하구나.\n아이구, 불에 구워지는 돼지야! 내 걱정은 말고\n너 죽어 가는 거나 걱정하거라.\n죽어 가는 것이 별 것을 다 걱정하고 있니?\n(※똥 묻은 개가 겨 묻은 개를 흉본다는 말과 같은 비유)",
            "soundUrl": "/media/wij",
            "image1Url": "/media/wyx",
            "category": "ADMIN",
            "count": "1074"
        },
        {
            "seq": "74",
            "type": "LB06",
            "name": "등땡이 고렵다",
            "siteName": "등허리가 가렵다",
            "contents": "여보, 나 등땡이 고렵다.\n어디, 영 홉서, 보게.\n아이구, 베렝이 물어싱게 마씸.\n약 볼라사 하쿠다.",
            "original": "여보, 나 등땡이 &#57767;렵다.\n어디 영 &#62790;서 보게.\n아이구, 베렝이 물어싱게마씸.\n약 &#58959;라사 허쿠다.",
            "solution": "여보 나 등허리가 가렵다.\n어디, 이렇게 하세요, 보게.\n아이구, 벌레가 물었네요.\n약 발라야 하겠습니다.\n(※마씸 : 마씀이라고도 함)",
            "soundUrl": "/media/wih",
            "image1Url": "/media/wyz",
            "category": "ADMIN",
            "count": "1360"
        },
        {
            "seq": "73",
            "type": "LB01",
            "name": "고랑은 몰라 마씀",
            "siteName": "말로 해서는 모릅니다",
            "contents": "제주도 비바리가 경도 좋으냐?\n고랑은 몰라 마씀.\n왕 봐사 알아집니다.\n모심도 좋고, 얼굴도 좋고, 집안도 좋아 마씀.",
            "original": "제주도 비바리가 경도 좋으냐?\n&#57773;앙은 몰라마씀.\n왕 봐사 알아집니다.\n&#58720;심도 좋고, 얼굴도 좋고, 집안도 좋아마씀.",
            "solution": "제주도 처녀가 그렇게도 좋으냐?\n말로 해서는 모릅니다.\n와서 보아야 알 수 있습니다.\n마음도 좋고, 얼굴도 좋고, 집안도 좋습니다.",
            "soundUrl": "/media/wig",
            "image1Url": "/media/wyl",
            "category": "ADMIN",
            "count": "1531"
        },
        {
            "seq": "72",
            "type": "LB06",
            "name": "무싱거 하미꽈?",
            "siteName": "무엇을 하십니까?",
            "contents": "무싱거 하미꽈? 혼저 옵서게.\n기여 알았저. 혼저 글라.\n푸더지질랑 말앙 옵서.\n돌, 조심호곡 고짝 옵세.",
            "original": "무싱거 허밍우과? &#62778;저 옵서게.\n기여 알앗저. 혼저 글라.\n푸더지질랑 말앙 옵서.\n돌 조심&#62775;곡 굳짝 옵서.",
            "solution": "무엇을 하십니까? 어서 오십시오.\n그래 알았다. 어서 가자.\n쓰러지지는 말고 오십시오.\n돌, 조심하고 곧장 오십시오.",
            "soundUrl": "/media/wif",
            "image1Url": "/media/wyk",
            "category": "ADMIN",
            "count": "1561"
        },
        {
            "seq": "71",
            "type": "LB06",
            "name": "아는 질도 들으멍 가라",
            "siteName": "아는 길도 물으면서 가라",
            "contents": "이젠, 니 인생은 니가 알앙 가야 혼다.\n알았수다. 잘 살크메 걱정 맙서.\n기여. 아는 질도 들으멍 가라.\n조심하멍 가는 질은 펜안혼다.",
            "original": "이젠 니 인생은 니가 알앙 가야 &#62778;다.\n알았수다. 잘 살크메 걱정 맙서.\n기여 아는 질도 들으멍 가라.\n조심허멍 가는 질은 펜안&#62778;다.",
            "solution": "이제는, 너의 인생은 네가 알아서 가야 한다.\n알았습니다. 잘 살겠으니 걱정 마십시오.\n그래. 아는 길도 물으면서 가라.\n조심하면서 가는 길은 편안하다.",
            "soundUrl": "/media/wid",
            "image1Url": "/media/wyj",
            "category": "ADMIN",
            "count": "1195"
        },
        {
            "seq": "70",
            "type": "LB05",
            "name": "어디 갔단 왐수과?",
            "siteName": "어디 갔다 오십니까?",
            "contents": "어디 갔단 왐수과?\n밭디 갔다 왐쩌. 어드레 감디?\n바당에 괴기 낚으레 감쑤다.\n절 쎄어서라. 조심호곡 혼저 오래.",
            "original": "어디 갓단 왐수과?\n밧디 갓다 왐저. 어드레 감디?\n바당에 궤기 나끄레 감수다.\n절 쎄어서라. 조심&#62775;곡 &#62778;저 오라.",
            "solution": "어디 갔다 오십니까?\n밭에 갔다 온다. 어디에 가느냐?\n바다에 고기 잡으로 갑니다.\n파도가 거세더라. 조심하고 일찍 오너라.",
            "soundUrl": "/media/wis",
            "image1Url": "/media/wyh",
            "category": "ADMIN",
            "count": "1265"
        },
        {
            "seq": "69",
            "type": "LB01",
            "name": "어떵 호코 마씀",
            "siteName": "어떻게 합니까",
            "contents": "강 보라. 니네 새서방 왔저.\n아이구, 부치루완 어떵 호코 마씀.\n앗다. 양양게 피우지 말라.\n혼저 가그네 '옵디가' 인사 호라.",
            "original": "강 보라. 니네 새서방 왓저.\n아이구, 부치루완 어떵&#62775;코마씀.\n앗다. 양양게 피우지 말라.\n&#62778;저가그네 '옵디가' 인사 &#62775;라.",
            "solution": "가서 보라. 너희 새신랑이 왔다.\n아이구, 부끄러워서 어떻게 합니까.\n어허. 호강에 넘친 소리 하지 마라.\n어서 가서 '오셨습니까'하고 인사 해라.",
            "soundUrl": "/media/wia",
            "image1Url": "/media/wyg",
            "category": "ADMIN",
            "count": "1131"
        },
        {
            "seq": "68",
            "type": "LB06",
            "name": "도르멍 옵서",
            "siteName": "빨리 오십시오",
            "contents": "무싱거 하미꽈? 도르멍 옵서.\n무사 경 다울렴디?\n해 저물민 어떵 홉니까?\n왁왁호민 질 잃어부렁 큰 일 납니다.",
            "original": "무싱거 험이과? &#58255;으멍 옵서.\n무사 경 다울렴디?\n해 저물민 어떵&#62790;니까?\n왁왁&#62775;민 질 잃어부렁 큰일 납니다.",
            "solution": "무엇을 하십니까? 빨리 오십시오.\n왜 그렇게 바쁘게 보채느냐?\n해 저물면 어떻게 합니까?\n캄캄하면 길 잃어버려 큰 일 납니다.",
            "soundUrl": "/media/wip",
            "image1Url": "/media/wyf",
            "category": "ADMIN",
            "count": "1919"
        },
        {
            "seq": "67",
            "type": "LB06",
            "name": "아방, 어멍 혼디 감쩌",
            "siteName": "아버지, 어머니 함께 가네",
            "contents": "저기 보라, 느네 아방, 어멍 혼디 감쩌.\n게메, 어디 감신고?\n하르방, 할망은 어신게!\n괸당집이 상 난에 감실거우다.",
            "original": "저기 보라 느네 아방 어멍 &#62778;디 감저.\n게메 어디 감신고?\n하르방, 할망은 어신게!\n&#44456;당집이 상 나네 감실거우다.",
            "solution": "저기 봐라, 너희 아버지, 어머니 함께 가네.\n글쎄, 어디 가고 있는가?\n할아버지, 할머니는 없네!\n친족집에 상을 당해서 가고 있을겁니다.",
            "soundUrl": "/media/wio",
            "image1Url": "/media/wyd",
            "category": "ADMIN",
            "count": "1855"
        },
        {
            "seq": "66",
            "type": "LB04",
            "name": "앞 낭에 아진 새야",
            "siteName": "앞 나무에 앉은 새야",
            "contents": "앞 낭에 아진 새야, 무사 경 울엄시냐?\n서울간 우리 서방, 재게 오랜 울엄시냐?\n저승 간 우리 어멍, 그리원 울엄시냐?\n내 모심, 아는 건 저 생이 뿐이구나.",
            "original": "앞 낭에 &#50522;인 새야, 무사 경 울엄시냐?\n서울간 우리 서방 재게 오렌 울엄시냐?\n저승 간 우리 어멍, 그리완 울엄시냐?\n내 &#58720;심 아는 건 저 생이 뿐이구나.",
            "solution": "앞 나무에 앉은 새야, 왜 그리 울고 있느냐?\n서울 간 우리 남편, 빨리 오라고 울고 있느냐?\n저승 간 우리 어머니, 그리워서 울고 있느냐?\n내 마음, 아는 건 저 새 뿐이로구나.",
            "soundUrl": "/media/wii",
            "image1Url": "/media/wys",
            "category": "ADMIN",
            "count": "1150"
        },
        {
            "seq": "65",
            "type": "LB01",
            "name": "느영 나영 소랑",
            "siteName": "너하고 나하고 사랑",
            "contents": "어드레 감쑤과? 이래 옵서.\n저들멍 살지 맙서.\n영 살아도 혼 세상, 정 살아도 혼 세상.\n두리 둥실 느영 나영 소랑이나 호게마씀.",
            "original": "어드레 감수과? 이레 옵서.\n저들멍 살지 맙서.\n영 살아도 &#62778; 세상, 정 살아도 &#62778; 세상.\n두리 둥실 느영 나영 &#59773;랑이나 &#62775;게.",
            "solution": "어디로 가십니까? 이리로 오십시오.\n걱정하면서 살지 마십시오.\n이렇게 살아도 한 세상, 저렇게 살아도 한 세상.\n둘이 둥실 너하고 나하고 사랑이나 합시다.\n( ※ 호게마씀 : ' 합시다' 의 강조말 )",
            "soundUrl": "/media/wiu",
            "image1Url": "/media/wya",
            "category": "ADMIN",
            "count": "1847"
        },
        {
            "seq": "64",
            "type": "LB06",
            "name": "솔문 독새기 호나 줍서",
            "siteName": "삶은 달걀이나 하나 주십시오",
            "contents": "돌코롬 혼 거 엇수과?\n게메, 어떵 것이 돌코롬 호코?\n사탕을 주카 마씀?\n아니우다. 게민 솔문 독새기나 호나 줍서.",
            "original": "&#58255;코롬 &#62778; 거 엇수과?\n게메 어떵 것이 &#58255;코롬 &#62775;코?\n사탕을 주카마씀?\n아니우다. 게민 &#59781;은 &#58251;세기나 &#62775;나 줍서.",
            "solution": "달콤한 거 없습니까?\n글쎄, 어떤 것이 달콤할까?\n사탕을 주면 어떻습니까?\n아닙니다. 그럼 삶은 달걀이나 하나 주십시오.",
            "soundUrl": "/media/wiy",
            "image1Url": "/media/wyp",
            "category": "ADMIN",
            "count": "1836"
        },
        {
            "seq": "63",
            "type": "LB06",
            "name": "들럭퀴지 말라",
            "siteName": "안절부절 날뛰지 말아라",
            "contents": "경 들럭퀴지 말라.\n초든초든 말 들엉 생각호라.\n어떵 혼 일인지 알아사 홀 꺼 아닌가?\n경 하당 숨 넘어 가키여!",
            "original": "경 들럭퀴지 말라.\n&#62273;든&#62273;든 말 들엉 생각&#62775;라.\n어떵&#62778; 일인지 알아사 &#62780; 거 아닌가?\n경 &#62775;당 숨 넘어 가키여!",
            "solution": "그렇게 안절부절 날뛰지 말아라.\n차근차근 말을 듣고서 생각해라.\n어떻게 된 일인지 알아야 할 것이 아니냐?\n그렇게 하다가 숨 넘어 가겠다!",
            "soundUrl": "/media/wit",
            "image1Url": "/media/wyo",
            "category": "ADMIN",
            "count": "1086"
        },
        {
            "seq": "62",
            "type": "LB01",
            "name": "무싱거옌 햄시니?",
            "siteName": "무엇이라고 귓속말을 하고 있느냐?",
            "contents": "무싱거옌 소곤닥 햄시니?\n비바리, 씨집 보내키옌 마씀.\n경 해사주게, 잘 생각했저.\n똘년은 나이 차민 혼저 보내 산다.",
            "original": "무싱거옌 소곤닥 헴시니?\n비바리 씨집 보내키옌마씀.\n경해사주게, 잘 셍각햇저.\n&#58344;년은 나이 차민 &#62778;저 보내 산다.",
            "solution": "무엇이라고 귓속말을 하고 있느냐?\n처녀, 시집 보내겠다고 말합니다.\n그렇게 해야지, 잘 생각했구나.\n딸은 나이가 들면 빨리(시집) 보내야 한다.",
            "soundUrl": "/media/wir",
            "image1Url": "/media/wyi",
            "category": "ADMIN",
            "count": "1265"
        },
        {
            "seq": "61",
            "type": "LB05",
            "name": "놀당 갑서",
            "siteName": "놀다가 가십시오",
            "contents": "들어 왕, 놀당 갑서.\n경 호카 마씀.\n여기, 불 조끄띠 안즙서. &#46627;&#46627;하우다.\n촘말, 맨도롱혼 게 좋수다.",
            "original": "들어 왕 놀당 갑서.\n경&#62775;카 마씀.\n여기 불 &#61948;꼇듸 안집서. &#58346;&#58346;하우다.\n&#62283;말, 멘도롱&#62778; 게 좋수다.",
            "solution": "들어 와서, 놀다가 가십시오.\n그렇게 할까요.\n여기, 불 옆으로 앉으십시오. 따뜻합니다.\n정말, 따뜻한 것이 좋습니다.",
            "soundUrl": "/media/wie",
            "image1Url": "/media/wyu",
            "category": "ADMIN",
            "count": "2007"
        },
        {
            "seq": "60",
            "type": "LB02",
            "name": "어떵 갑니까?",
            "siteName": "어떻게 갑니까?",
            "contents": "한락산드레 가젱 호민 어떵 갑니까?\n바당드렌 어떵 갑니까?\n차 타젱 호민, 하영 가사 홉니까?\n제주도엔 가당 봐도 바당이우다, 양!",
            "original": "할락산드레 가젱 &#62775;민 어떵 갑니까?\n바당드렌 어떵 갑니까?\n차 타젱 &#62775;민 하영 가사 &#62790;니까?\n제주도엔 가당 봐도 바당이우다양!",
            "solution": "한라산으로 가려 하면 어떻게 갑니까?\n바다에는 어떻게 갑니까?\n차를 타려고 하면, 많이 가야 합니까?\n제주도엔 가다가 봐도 바다입니다, 예!",
            "soundUrl": "/media/wiw",
            "image1Url": "/media/wyy",
            "category": "ADMIN",
            "count": "1457"
        },
        {
            "seq": "59",
            "type": "LB06",
            "name": "호꼼 미안하우다",
            "siteName": "좀 실례합니다",
            "contents": "호꼼 미안하우다. 이게 얼마꽈?\n오천원 마씀.\n호꼼만 싸게 안되카 마씀?\n경 해사, 다시 올 거 아니꽈?",
            "original": "&#62775;꼼 미안허우다. 이게 얼마과?\n오천원마씀.\n&#62775;꼼만 싸게 안뒈카마씀?\n경헤사 다시 올 거 아니과?",
            "solution": "좀 실례합니다. 이 것이 얼마입니까?\n오천원 입니다.\n조금만 싸게 안될까요?\n그렇게 해야, 다시 올 거 아닙니까?",
            "soundUrl": "/media/wiq",
            "image1Url": "/media/wyt",
            "category": "ADMIN",
            "count": "1427"
        },
        {
            "seq": "58",
            "type": "LB06",
            "name": "몬뜰락 벗응거 봅서",
            "siteName": "모조리 벗은 것 보시오",
            "contents": "저기, 요새 애들 옷 입언 댕기는 거 봅서.\n허벅지도 내 놓곡, 베또롱도 내 놓곡,\n그거, 무슨 요망들이라!\n경 말앙, 몬뜰락 벗엉 댕기주 게.",
            "original": "저기 요새 애들 옷 입언 뎅기는 거 봅서.\n허벅지도 내 놓곡, 베또롱도 내 놓곡,\n그거 무슨 요망들이라!\n경 말앙, &#58723;들락 벗엉 뎅기주게.",
            "solution": "저기, 요새 애들 옷 입고서 다니는 것 보십시오.\n허벅다리도 내 놓고, 배꼽도 내 놓고,\n그게, 무슨 별짓들이야!\n그러지 말고, 모조리 벗고서 다니지.",
            "soundUrl": "/media/wuM",
            "image1Url": "/media/wyr",
            "category": "ADMIN",
            "count": "1278"
        },
        {
            "seq": "57",
            "type": "LB06",
            "name": "짐진 놈이 팡을 촛나",
            "siteName": "짐을 진 사람이 짐 부릴 곳을 찾는다",
            "contents": "어멍이영 고치 옵세.\n오당그네, 영 호곡, 정 호곡 홉서.\n무사, 경 숨 고끼멍 고람서?\n짐 진놈이 팡을 촛주게.\n게난, 걱정 말앙 고만이 이서.",
            "original": "어멍이영 &#57767;치 옵서.\n오당그네, 영&#62775;곡, 정&#62775;곡 &#62790;서.\n무사 경 숨 &#57767;끼멍 &#57773;암서?\n짐 진 놈이 팡을 &#62289;주게.\n게난 걱정 말앙 &#57767;만이 이서.",
            "solution": "어머니랑 같이 오십시오.\n오다가, 이렇게 하고, 저렇게 하고 하십시오.\n왜, 그렇게 숨차게(급하게) 말하는가?\n짐을 진 사람이 짐 부릴 곳을 찾는 법이네.\n그러니, 걱정 말고서 가만히 있게.",
            "soundUrl": "/media/wuN",
            "image1Url": "/media/wye",
            "category": "ADMIN",
            "count": "1006"
        },
        {
            "seq": "56",
            "type": "LB06",
            "name": "솔째기 골라",
            "siteName": "살그머니 말해라",
            "contents": "소랑 홀 땐 솔째기 골라.\n누게 들엉 웃나.\n아무도 몰르게\n느영 나영만 솔째기 호게.",
            "original": "&#59773;랑홀 땐 &#59778;째기 &#57773;라.\n누게 들엉 웃나.\n아무도 몰르게\n느영 나영만 &#59778;째기 &#62775;게.",
            "solution": "사랑 할 때는 살그머니 말해라.\n누가 들으면 웃는다.\n아무도 모르게\n너하고 나하고만 살그머니 하자.\n( ※ 솔째기 : 살그머니 )",
            "soundUrl": "/media/wuB",
            "image1Url": "/media/wyw",
            "category": "ADMIN",
            "count": "1160"
        },
        {
            "seq": "55",
            "type": "LB02",
            "name": "꽝이 복삭 하우다",
            "siteName": "뼈가 폭삭 주저앉는다",
            "contents": "아척부터 조녁까지, 두리 둥실\n사랑 호곡, 구경 호곡,\n경 호단 보난, 꽝이 복삭하우다.",
            "original": "아척부터 &#61948;냑까지, 두리둥실\n&#59773;랑&#62775;곡, 구경&#62775;곡,\n경&#62775;단 보난 꽝이 복삭허우다.",
            "solution": "아침부터 저녁까지, 두 사람이 둥실\n사랑도 하고, 구경도 하고,\n그렇게 하다 보니 뼈가 폭삭 주저앉는다.\n( ※ 복삭하다 : 풀썩 주저앉고 싶게 지치고 힘들다)",
            "soundUrl": "/media/wuV",
            "image1Url": "/media/wyq",
            "category": "ADMIN",
            "count": "1170"
        },
        {
            "seq": "54",
            "type": "LB06",
            "name": "호꼼 있당 와 줍서",
            "siteName": "조금 있다가 와 주십시오",
            "contents": "오늘랑 우리 밭디 마농 심거 줍서.\n경 홉주마! 겐디, 비 옴직 해염쑤다.\n동그레 구름이 시커멍 햄신게 마씀.\n게민, 호꼼 있당 와 줍서",
            "original": "오늘랑 우리 밧듸 마농 싱거 줍서.\n경 &#62790;주마! 겐디 비 옴직 헤염수다.\n동드레 구름이 시커멍 헴신게마씀.\n게민 &#62775;꼼 잇당 와 줍서",
            "solution": "오늘은 우리 밭에 마늘 심어 주십시오.\n그렇게 합시다! 그런데, 비가 올 것 같습니다.\n동쪽으로 구름이 시커멓게 되고 있습니다.\n그럼, 조금 있다가 와 주십시오.",
            "soundUrl": "/media/wuC",
            "image1Url": "/media/wtM",
            "category": "ADMIN",
            "count": "1285"
        },
        {
            "seq": "53",
            "type": "LB01",
            "name": "강 돌앙 옵서",
            "siteName": "가서, 데리고 오십시오",
            "contents": "새 각씨, 무사 안 왐쑤과?\n어떵 된 거 아니우꽈?\n강, 돌앙 옵서.\n무신걸 경 몽캠신고?",
            "original": "새각씨, 무사 안 왐수과?\n어떵 &#46220; 거 아니우과?\n강 &#58255;앙 옵서.\n무신걸 경 몽켐신고?",
            "solution": "색씨, 왜 안 옵니까?\n어떻게 된 거 아닙니까?\n가서, 데리고 오십시오.\n무었을 그렇게 늑장부리고 있는 건가?",
            "soundUrl": "/media/wuX",
            "image1Url": "/media/wtN",
            "category": "ADMIN",
            "count": "1202"
        },
        {
            "seq": "52",
            "type": "LB06",
            "name": "옴짝 못핸 살암서라",
            "siteName": "꼼짝 못해서 살고 있더라",
            "contents": "서울서 온 소나이\n제주 비바리에 미쳐 부런\n오늘 가카, 넬 가카, 호단 보난\n옴짝 못핸 살암서라.",
            "original": "서울서 온 &#59773;나이\n제주 비바리에 미쳐부런\n오늘 가카 넬 가카 &#62775;단 보난\n옴짝 못헨 살암서라.",
            "solution": "서울에서 온 사나이\n제주 처녀에 미쳐 버리니까\n오늘 갈까, 내일 갈까, 하다가 보니\n꼼짝 못해서 살고 있더라.",
            "soundUrl": "/media/wuZ",
            "image1Url": "/media/wtB",
            "category": "ADMIN",
            "count": "1435"
        },
        {
            "seq": "51",
            "type": "LB02",
            "name": "한림공원에 강 봅서",
            "siteName": "한림공원에 가보세요?",
            "contents": "한림공원에 강 봅디가?\n밸의 밸, 낭이랑 꽃이랑 잘도 곱디다.\n소랑호는 사롬은 꼭 강 봐사 혼댄 마씀.\n경 해사, 소랑호멍 잘 산댄 고릅디다.",
            "original": "한림공원에 강 봅디가?\n벨이벨, 낭이랑 꼿이랑 잘도 곱디다.\n&#59773;랑&#62775;는 사롬은 꼭 강 봐사 &#62778;덴 마씀.\n경헤사, &#59773;랑&#62775;멍 잘 산덴 &#57773;읍디다.",
            "solution": "한림공원에 가서 보았습니까?\n별의 별, 나무랑 꽃이랑 잘도 아름답습니다.\n사랑하는 사람은 꼭 가서 봐야 한다고 합니다.\n그래야, 사랑하면서 잘 산다고 합니다.",
            "soundUrl": "/media/wuL",
            "image1Url": "/media/wtV",
            "category": "ADMIN",
            "count": "1266"
        },
        {
            "seq": "50",
            "type": "LB07",
            "name": "허천 베레지 말라",
            "siteName": "한눈 팔아서 가지 말아라",
            "contents": "살당 보민 고생홀 때도 있곡,\n어려웡 쓸어질 때도 있저.\n경해도, 허천 베레지 말라.\n곳작 호게 걸어 감시민\n나종엔 꼭 성공혼다.",
            "original": "살당 보민 고생&#62780; 때도 잇곡,\n어려왕 쓰러질 때도 잇저.\n경헤도 허천 베레지 말라.\n곧작&#62775;게 걸어감시민\n나종엔 꼭 성공&#62778;다.",
            "solution": "살다 보면 고생할 때도 있고, \n어려워서 쓰러질 때도 있단다.\n그래도, 한눈 팔아서 가지 말아라.\n곧게 걸어 가노라면\n나중엔 꼭 성공한다.",
            "soundUrl": "/media/wuK",
            "image1Url": "/media/wtC",
            "category": "ADMIN",
            "count": "2960"
        },
        {
            "seq": "49",
            "type": "LB07",
            "name": "두렁청 호게 다울리지 말라",
            "siteName": "정신없이 급하게 재촉해서 일하지 마라",
            "contents": "두렁청 호게 다울리멍 일호지 말라.\n바농 존둥이 졸라 메영\n바농질 되는 거 봔디야?\n촌촌히 생각호멍\n호나씩 해사 일이 된다.",
            "original": "두령청&#62775;게 다울리멍 일&#62775;지 말라.\n바농 &#61950;둥이 &#61952;라메영\n바농질 뒈는 거 봔디야?\n&#62275;&#62275;히 생각&#62775;멍\n&#62775;나씩 해사 일이 &#46220;다.",
            "solution": "정신없이 급하게 재촉해서 일하지 마라.\n바늘 허리를 졸라 매어서\n바느질 되는 거 봤느냐?\n천천히 생각하면서\n하나씩 해야 일이 된다.",
            "soundUrl": "/media/wuJ",
            "image1Url": "/media/wtX",
            "category": "ADMIN",
            "count": "1861"
        },
        {
            "seq": "48",
            "type": "LB04",
            "name": "제주도 민요 - 해녀 노래",
            "siteName": "제주도 민요 - 해녀 노래",
            "contents": "요 바당에, 요 물에 들언\n좀복, 구젱기, 고득하게 잡아당\n혼 푼, 두 푼, 모이단 보난\n서방님 술깝에 몬딱 들어 감쩌.",
            "original": "요 바당에, 요 물에 들언\n&#61956;복, 구젱기, &#57767;득하게 잡아당\n&#62778; 푼, 두 푼, 모이단 보난\n서방님 술깝에 &#58723;딱 들어감저.",
            "solution": "여기 바다에, 여기 물에 들어가서\n전복, 소라, 가득하게 잡아다가\n한 푼, 두 푼, 모이다 보니까\n남편의 술값에 모조리 들어 가더라.\n( ※ 남편을 원망하는 해녀인 아내의 노래 )",
            "soundUrl": "/media/wuH",
            "image1Url": "/media/wtZ",
            "category": "ADMIN",
            "count": "1669"
        },
        {
            "seq": "47",
            "type": "LB04",
            "name": "제주도 민요 - 시집살이 노래",
            "siteName": "제주도 민요 - 시집살이 노래",
            "contents": "독이사 울엉 날이 새주마는,\n내사 울엉 어느 날 새리.\n독의 목에 통쇠나 종강\n내가 대신 울어나 보카.",
            "original": "&#58251;이사 울엉 날이 새주마는,\n내사 울엉 어느 날 새리.\n&#58251;의 목에 통쒜나 &#61963;강\n내가 대신 울어나 보카.",
            "solution": "닭이야 울면 날이 밝아 오지만, \n내가 울면 어느 날 밝을 수 있으랴.\n닭의 목에 자물쇠나 잠궈서\n내가 대신 울어나 볼까.\n( ※ 시집살이에서 고생하는 며느리의 한 맺힌 노래 )",
            "soundUrl": "/media/wuG",
            "image1Url": "/media/wtL",
            "category": "ADMIN",
            "count": "1568"
        },
        {
            "seq": "46",
            "type": "LB06",
            "name": "경 호곡 말곡",
            "siteName": "그렇고 말고",
            "contents": "어멍이 용심 난, 옴찍 안햄쑤다.\n경 호곡 말곡!\n믿던 낭에 곰팽이 핀댕 행게마는, \n하도 억울호게 당해부런 아니가.\n어멍 모심 달래 드리라!",
            "original": "어멍이 용심난, 옴찍 안햄수다.\n경 &#62775;곡 말곡!\n믿던 낭에 곰펭이 핀덴 헹게마는 \n하도 억울&#62775;게 당헤부런 아니가.\n어멍 &#58720;심 달레 드리라!",
            "solution": "어머니가 화가 나서, 꼼짝 안합니다.\n그렇고 말고!\n믿던 나무에 곰팡이가 핀다고 하더니만,\n하도 억울하게 당해서 아니냐.\n어머니 마음 위로해 드려라!",
            "soundUrl": "/media/wuF",
            "image1Url": "/media/wtK",
            "category": "ADMIN",
            "count": "1596"
        },
        {
            "seq": "45",
            "type": "LB06",
            "name": "지 껏은 족아 벤다",
            "siteName": "자기 것은 작게 보인다",
            "contents": "무사, 난 호꼼만 &#51496;쑤과?\n이놈아! 욕심 먹은 눈에는\n지 껏이 족아 베곡,\n놈의 껏은 커 베는 거여!\n똑고치 나눈 것을 어찌 크다 족다 햄시니?",
            "original": "무사, 난 &#62775;꼬만 &#51496;수과?\n이놈아! 욕심 먹은 눈에는\n지 것이 &#61949;아 베곡,\n&#58000;의 것은 커 베는 거여!\n똑&#57767;치 나눈 것을 어찌 크다 &#61949;다 헴시니?",
            "solution": "왜, 나는 조그만 줍니까?\n이놈아! 욕심을 가진 눈에는\n자기 것은 작게 보이고,\n남의 것은 크게 보이는 것이야!\n똑같이 나눈 것을 어찌 크다 작다 하느냐?",
            "soundUrl": "/media/wuD",
            "image1Url": "/media/wtJ",
            "category": "ADMIN",
            "count": "786"
        },
        {
            "seq": "44",
            "type": "LB02",
            "name": "무신 걸 먹으코?",
            "siteName": "무엇을 먹을까?",
            "contents": "무신 걸 먹으코?\n게메 양, 제주도에만 이신 거 먹게 마씀.\n그젱기에, 보말에, 옥돔생성,\n또 있수다. 모멀 범벅에 자리젯!\n먹을 것도 촘 하영 있저.",
            "original": "무신 걸 먹으코?\n게메양, 제주도에만 이신 거 먹게마씀.\n구젱기에, 보말에, 옥돔생성,\n또 잇수다. 모멀범벅에 자리젯!\n먹을 것도 &#62283; 하영 있저.",
            "solution": "무엇을 먹을까?\n글쎄요, 제주도에만 있는 것을 먹읍시다.\n소라에, 보말(조그만 바다 소라)에, 옥돔생선,\n또 있어요. 메밀 범벅에 자리젓갈!\n먹을 것도 참 많이 있네.",
            "soundUrl": "/media/wuS",
            "image1Url": "/media/wtH",
            "category": "ADMIN",
            "count": "1514"
        },
        {
            "seq": "43",
            "type": "LB03",
            "name": "야게기와 저깽이",
            "siteName": "목아지에 때를 밀라",
            "contents": "야게기에 때 밀라.\n저깽이영, 정겡이도 밀곡,\n옷 벗엉, 강알 트멍도 밀라.\n사롬 몸은 곱닥해사 혼다.",
            "original": "야게기에 때 밀라.\n&#61948;깽이영, 정겡이도 밀곡,\n옷 벗엉, 강알 트멍도 밀라.\n사롬 몸은 곱닥해사 &#62778;다.",
            "solution": "목아지에 때를 밀라.\n겨드랑이랑, 종아리(정강이)도 밀고,\n옷 벗어서, 사타구니 사이도 밀어라.\n사람 몸은 깨끗해야 한다.",
            "soundUrl": "/media/wuA",
            "image1Url": "/media/wtG",
            "category": "ADMIN",
            "count": "1118"
        },
        {
            "seq": "42",
            "type": "LB06",
            "name": "짐 촐리라",
            "siteName": "짐 꾸려라",
            "contents": "이제 가게, 짐 촐리라.\n알았수다. 아이덜도 도랑 가카 마씀?\n기여, 모딱 고치 가게.\n하르방, 할망이 좋아할거여.",
            "original": "이제 가게, 짐 &#62277;리라.\n알앗수다. 아이덜도 &#58255;앙 가카마씀?\n기여, &#58723;딱 &#57767;치 가게.\n하르방, 할망이 좋아헐거여.",
            "solution": "이제 가자, 짐 꾸려라.\n알았습니다. 아이들도 데리고 갈까요?\n그래, 모두 같이 가자.\n할아버지, 할머니가 좋아하실거야.",
            "soundUrl": "/media/wuP",
            "image1Url": "/media/wtF",
            "category": "ADMIN",
            "count": "866"
        },
        {
            "seq": "41",
            "type": "LB06",
            "name": "그거 앗아도라",
            "siteName": "그거 가져다 줘라",
            "contents": "새각씨야, 그거 앗아 도라.\n무사, 당신은 손 엇수과? 발 엇수과?\n경 호지 말앙 좀 앗아 주민 어떵 호느냐?\n버릇나 마씀!\n밸 놈의 요망진 소리 그만 호라.",
            "original": "새각씨야, 그거 앗아 &#58250;라.\n무사, 당신은 손 엇수과? 발 엇수과?\n경&#62775;지 말앙 좀 앗아 주민 어떵 &#62775;느냐?\n버릇나마씀!\n벨 놈의 요망진 소리 그만 &#62775;라.",
            "solution": "색씨, 그거 가져다 줘라.\n왜, 당신은 손이 없어요? 발이 없어요?\n그러지 말고 좀 가져다 주면 안돼냐?\n버릇 됩니다!\n별나고 약아 빠진 소리 그만 해라.",
            "soundUrl": "/media/wuO",
            "image1Url": "/media/wtD",
            "category": "ADMIN",
            "count": "951"
        },
        {
            "seq": "40",
            "type": "LB06",
            "name": "와리지 말앙 골라",
            "siteName": "너무 서두르지 말고, 천천히 말해 보아라",
            "contents": "아이구 게, 큰일 났수다.\n무사, 경 들락켬시니?\n와리지 말앙, 촌촌이 고라 보게.\n경호난 양, 영 호곡, 정 호곡 했수게.\n게난, 욕심 내멍 살민 경 혼다.",
            "original": "아이구게, 큰일낫수다.\n무사, 경 들락퀴엄시니?\n와리지 말앙, &#62275;&#62275;이 &#57773;앙 보게.\n경&#62775;난양, 영&#62775;곡, 정&#62775;곡 헷수게.\n게난 욕심 내멍 살민 경&#62778;다.",
            "solution": "아이구(강함), 큰일 났습니다.\n왜, 그렇게 들락키느냐?\n너무 서두르지 말고, 천천히 말해 보아라.\n그러니까요, 이렇게 하고, 저렇게 하고 했습니다.\n그러니까, 욕심 내면서 살면 그렇게 된다.",
            "soundUrl": "/media/wuI",
            "image1Url": "/media/wtS",
            "category": "ADMIN",
            "count": "1263"
        },
        {
            "seq": "39",
            "type": "LB06",
            "name": "요 년 난거 보라",
            "siteName": "요 계집애 봐라",
            "contents": "요 년 난거 보라.\n놈이 소나이영 말 호곡, 벌써부터 서방질 햄시냐?\n아니우다 게. 바당드레 가단,\n질 모른 사롬 이시난 질 고르쳐 줬수게.",
            "original": "요년 난 거 보라.\n&#58000;이 소나이영 말 &#62775;곡, 벌써부터 서방질 햄시냐?\n아니우다게. 바당드레 가단,\n질 몰른 사롬 이시난 질 &#57767;르쳐 줘수게.",
            "solution": "요 계집애 봐라.\n남의 남자와 얘기 하고, 벌써부터 남자를 밝히느냐?\n아닙니다. 바다에 가다가,\n길 모르는 사람이 있어서 길 가르켜 줬습니다.\n( ※ 요 년 난거 : 어린 처녀를 욕할때 많이 쓰임)",
            "soundUrl": "/media/wuU",
            "image1Url": "/media/wtA",
            "category": "ADMIN",
            "count": "830"
        },
        {
            "seq": "38",
            "type": "LB06",
            "name": "쌍둥이 고름배기",
            "siteName": "쌍둥이 다툼",
            "contents": "쌍둥이 어멍! 고생햄쭈, 이?\n둘이가 고름배기 해연 죽어지쿠다.\n경 홀거라.\n게도, 놈 호고 싸울 땐\n지네 펜백들멍 싸워 마씀.",
            "original": "쌍둥이 어멍! 고생햄주, 이?\n둘리가 &#57773;른배기 헤연 죽어지쿠다.\n경 &#62780;거라.\n게도, &#58000; 호고 싸울 땐\n지네 펜벡들멍 싸와 마씀.",
            "solution": "쌍둥이 어머니! 고생하고 있네요, 그렇지요?\n둘이가 서로 이기려고 하니 죽겠습니다.\n그렇게 할 거에요.\n그래도, 남하고 싸울 때는\n자기네 편을 들면서 싸웁니다.",
            "soundUrl": "/media/wuY",
            "image1Url": "/media/wtP",
            "category": "ADMIN",
            "count": "965"
        },
        {
            "seq": "37",
            "type": "LB06",
            "name": "욕 하는 소리들",
            "siteName": "욕 하는 소리들",
            "contents": "그 나쁜 놈! 볼망텡이를 박아 불거 아니꽈?\n경 했주! 모가지 잡안 흥글단,\n대맹이로 뱃대기를 박아 부난,\n둥글멍 자빠정게!\n잘 콰니여! 그런 놈은 혼내 줘사 홉니다.",
            "original": "그 나쁜 놈! 볼망텡이를 박아불 거 아니과?\n경헷주! 모가지 잡안 흥글단,\n데망이로 벳데기를 박아부난,\n둥글멍 자빠정게!\n잘&#62442;사니여! 그런 놈은 혼내 줘사 &#62790;니다.",
            "solution": "그 나쁜 놈! 뺨따귀를 때려 버릴거 아닙니까?\n그렇게 했어! 목을 잡아서 흔들다가,\n머리로 배를 받아 버렸더니,\n뒹글며 쓰러져 버리더군!\n잘 됐어! 그런 놈은 혼을 내 줘야 합니다.",
            "soundUrl": "/media/wuT",
            "image1Url": "/media/wtO",
            "category": "ADMIN",
            "count": "1048"
        },
        {
            "seq": "36",
            "type": "LB01",
            "name": "서울 새각씨",
            "siteName": "서울 색씨",
            "contents": "서울서 새각씨 왔수다.\n어떵 생겨서?\n요망지게 생겨십디다.\n솔째기 웃으멍 말 호는 거 보난, 착햄직 홉디다.",
            "original": "서울서 새각씨 왓수다.\n어떵 생겨서?\n요망지게 생겨십디다.\n&#59778;째기 웃으멍 말&#62775;는 거 보난, 착헴직 &#62790;디다.",
            "solution": "서울에서 색씨가 왔습니다.\n어떻게 생겼던가?\n똑똑하고 영리하게 생겼습니다.\n살그머니 웃으면서 말 하는 걸 보니, 착할 것 같습니다.",
            "soundUrl": "/media/wuR",
            "image1Url": "/media/wtI",
            "category": "ADMIN",
            "count": "886"
        },
        {
            "seq": "35",
            "type": "LB03",
            "name": "제주 바당은 소랑이우다",
            "siteName": "제주 바다는 사랑입니다",
            "contents": "제주 바당에 강 봅서.\n미운 것도 엇어지곡, 슬픈것도 엇어지곡,\n가슴으로 바당물만 들곡 나곡 호멍\n두리 둥실 둥그대 당실\n소랑만 고득하게 담앙 옵니다.",
            "original": "제주 바당에 강 봅서.\n미운 것도 엇어지곡, 슬픈 것도 엇어지곡,\n가슴으로 바당물만 들곡 나곡 &#62775;멍\n두리 둥실 둥그대 당실\n&#59773;랑만 &#57767;득하게 담앙 옵니다.",
            "solution": "제주 바다에 가서 보십시오.\n미운 것도 없어지고, 슬픈것도 없어지고,\n가슴으로 바닷물만 들어오고 나가고 하면서\n둘이 둥실 둥그대 당실 ( 제주도의 흥겨운 민요가락 )\n사랑만 가득하게 담아서 옵니다.",
            "soundUrl": "/media/wuE",
            "image1Url": "/media/wtU",
            "category": "ADMIN",
            "count": "1663"
        },
        {
            "seq": "34",
            "type": "LB03",
            "name": "제주 바당은 꽃이우다",
            "siteName": "제주 바다는 꽃입니다",
            "contents": "제주 바당에 가민 바당이 말을 홉니다.\n사롬보다 더 조잘조잘 말을 하곡\n사롬보다 더 소랑도 하영 홉니다.\n경 호멍, 낮이나 밤이나 \n꽃을 피웠당, 지웠당 홉니다.",
            "original": "제주 바당에 가민 바당이 말을 &#62790;니다.\n사롬보다 더 조잘조잘 말을 허곡\n사롬보다 더 &#59773;랑도 하영 &#62790;니다.\n경&#62775;멍, 낮이나 밤이나 \n꼿을 피왓당, 지왓당 &#62790;니다.",
            "solution": "제주 바다에 가면 바다가 말을 합니다.\n사람보다 더 재잘재잘 말을 하고\n사람보다 더 사랑도 많이 합니다.\n그렇게 하면서, 낮이나 밤이나\n꽃을 피웠다가, 지웠다가 합니다.",
            "soundUrl": "/media/wuW",
            "image1Url": "/media/wtY",
            "category": "ADMIN",
            "count": "1415"
        },
        {
            "seq": "33",
            "type": "LB06",
            "name": "일 호젠 호난 속았수다",
            "siteName": "일 하려고 하니 수고 했습니다",
            "contents": "과랑 과랑혼 벳디\n일 호젠 호난 속았수다.\n속을 거 있수과? 호꼼, &#46624;은 났수다만,\n안트레 들어 왕, 조녁 먹엉 갑서.\n경 호카 마씀.",
            "original": "과랑과랑&#62778; 벳디\n일&#62775;젠 &#62775;난 속앗수다.\n속을 거 잇수과? &#62775;꼼, &#58345;은 낫수다만,\n안트레 들어왕, &#61948;냑 먹엉 갑서.\n경&#62775;카마씀.",
            "solution": "쨍쨍한 햇볕속에\n일 하려고 하니 수고 했습니다.\n수고 할 거 있습니까? 조금, 땀은 났습니다만,\n안으로 들어 오셔서, 저녁식사 하고 가십시오.\n그렇게 할까요.",
            "soundUrl": "/media/wuQ",
            "image1Url": "/media/wtT",
            "category": "ADMIN",
            "count": "1200"
        },
        {
            "seq": "32",
            "type": "LB02",
            "name": "돌코롬 혼 전복죽",
            "siteName": "달고 맛있는 전복죽",
            "contents": "둘이 먹당, 호나 죽어도 몰르는 건 무신거꽈?\n돌코롬 혼 제주도 전복죽이주!\n둘이 보당, 호나 죽어도 몰르는 건 무신거꽈?\n곱들락 혼 제주도 비바리주!\n게민 옵서. 전복죽 먹곡 비바리 보래 가게 마씀.",
            "original": "둘이 먹당, &#62775;나 죽어도 몰르는 건 무신거과?\n&#58255;코롬&#62778; 제주도 전복죽이주!\n둘이 보당 &#62775;나 죽어도 몰르는 건 무신거꽈?\n곱들락&#62778; 제주도 비바리주!\n게민 옵서. 전복죽 먹곡 비바리 보레 가게마씀.",
            "solution": "둘이 먹다가, 한 명이 죽어도 모르는 건 무엇입니까?\n달고 맛있는 제주도 전복죽이야!\n둘이 보다가, 한 사람이 죽어도 모르는 건 무엇입니까?\n곱고 예쁘장한 제주도 처녀야!\n그러면 오십시오. 전복죽 먹고서 처녀 보러 갑시다.",
            "soundUrl": "/media/wum",
            "image1Url": "/media/wtR",
            "category": "ADMIN",
            "count": "1265"
        },
        {
            "seq": "31",
            "type": "LB06",
            "name": "제주도에서 살게 마씀",
            "siteName": "제주도에서 삽시다",
            "contents": "서방님, 제주도에서 살게 마씀\n좋주마, 널은 바당, 좋은 공기,\n인심좋은 사롬들광 살민 살 맛 날거라.\n살당 지치민, 풍덩 바당에 들어 가곡 마씀.",
            "original": "서방님, 제주도에서 살게마씀\n좋주마, 널른 바당, 좋은 공기,\n인심 좋은 사롬들광 살민 살맛 날거라.\n살당 지치민, 풍덩 바당에 들어가곡마씀.",
            "solution": "여보, 제주도에서 삽시다.\n좋지요, 넓은 바다, 좋은 공기,\n인심좋은 사람들과 살면 살 맛 날거다.\n살다가 지치면, 풍덩 바다에 들어 가고 말입니다.",
            "soundUrl": "/media/wun",
            "image1Url": "/media/wtE",
            "category": "ADMIN",
            "count": "1063"
        },
        {
            "seq": "30",
            "type": "LB05",
            "name": "영 호곡, 정 호곡 홉서(짧게 생략한 신기한 사투리들)",
            "siteName": "이렇게  하고, 저렇게 하고 하십시오",
            "contents": "강, 방 옵서.\n왕, 방 삽서.\n영 호곡, 정 호곡 홉서.\n경 고라 줍서.\n가지 말앙, 영 호멍 삽서.",
            "original": "강 방 옵서.\n왕 방 삽서.\n영호곡, 정&#62775;곡 &#62790;서.\n경 &#57773;아 줍서.\n가지 말앙, 영&#62775;멍 삽서.",
            "solution": "가서 보고 오십시오.\n와서 보고 사십시오.\n이렇게 하고, 저렇게 하고 하십시오.\n그렇게 말해 주십시오.\n가지 말고서 이렇게 하면서 사십시오.",
            "soundUrl": "/media/wub",
            "image1Url": "/media/wtW",
            "category": "ADMIN",
            "count": "1464"
        },
        {
            "seq": "29",
            "type": "LB06",
            "name": "두 가시가 어드레 감서?",
            "siteName": "두 부부가 어디로 가는가?",
            "contents": "두 가시가 어드레 경 돌암서?\n큰 똘, 애기 낫댄 햄 감쑤다.\n경 했구나. 무슨 애기 나서?\n아덜 마씀!\n아이고, 잘 됐구나게! 혼저 강 봐 게.",
            "original": "두 가시가 어드레 경 &#58255;암서?\n큰 &#58344;, 애기 낫덴 헴 감수다.\n경 헷구나. 무슨 애기 나서?\n아덜마씀!\n아이고, 잘 &#46235;구나게! &#62778;저 강봐게.",
            "solution": "두 부부가 어디로 그렇게 달려 가는가?\n큰 딸이 아이를 낳았다고 해서 갑니다.\n그랬구나. 무슨 애기를 낳았는가?\n아들 입니다!\n아이구, 잘 되었네! 어서 가 보게나.",
            "soundUrl": "/media/wuv",
            "image1Url": "/media/wtQ",
            "category": "ADMIN",
            "count": "1351"
        },
        {
            "seq": "28",
            "type": "LB07",
            "name": "소도리 호지 맙서",
            "siteName": "소문 옮기면서 다니지 마십시오",
            "contents": "소도리 행 댕기지 맙서.\n소도리는 놈덜 싸움만 맨듭니다.\n옛부터 싸움은 멀리곡, 흥정은 부치렌 했수다.\n게난, 좋은 소린 크게 호곡, \n궂은 소린 속솜 해 붑서.",
            "original": "소도리 헹 뎅기지 맙서.\n소도리는 놈덜 싸움만 멘듭니다.\n옛부터 싸움은 멀리곡, 흥정은 부치렌 했수다.\n게난, 좋은 소린 크게 &#62775;곡,\n궂은 소린 속솜해 붑서.",
            "solution": "소문 옮기면서 다니지 마십시오.\n소문은 남들 싸움만 만듭니다.\n예부터 싸움은 말리고, 흥정은 붙이라고 했습니다.\n그러니, 좋은 소리는 크게 하고,\n나쁜 소리는 조용히 해 버리십시오.",
            "soundUrl": "/media/wuc",
            "image1Url": "/media/wtm",
            "category": "ADMIN",
            "count": "1276"
        },
        {
            "seq": "27",
            "type": "LB06",
            "name": "무상고 마씀",
            "siteName": "무엇 때문인가요?",
            "contents": "어멍이 해 준 밥 먹어 봅서.\n촘말로 맛이 좋수다.\n무상고 마씀?\n그건 어머님의 사랑호는 모심이\n밥속에 고득 고득 들어 이시난 아니꽈.",
            "original": "어멍이 해 준 밥 먹어 봅서.\n&#62283;말로 맛이 좋수다.\n무상고마씀?\n그건 어머님의 &#59773;랑&#62775;는 &#58720;심이\n밥속에 고득고득 들어 이시난 아니과?",
            "solution": "어머니가 해 준 밥을 먹어 보십시오.\n정말로 맛이 좋습니다.\n무엇 때문인가요?\n그건 어머니의 사랑하는 마음이\n밥속에 가득 가득히 들어 있기 때문 아닙니까.",
            "soundUrl": "/media/wux",
            "image1Url": "/media/wtn",
            "category": "ADMIN",
            "count": "884"
        },
        {
            "seq": "26",
            "type": "LB06",
            "name": "멩심허영 갔당 옵서",
            "siteName": "조심해서 갔다 오십시오",
            "contents": "어드레 감수과?\n바당에 괴기 사레 마씀.\n무사, 누게 왔수과?\n서울서 족은 아방네 완 마씀. \n게민, 멩심허영 갔당 옵서.",
            "original": "어드레 감수과?\n바당에 궤기 사레마씀.\n무사, 누게 왓수과?\n서울서 족은아방네 완마씀.\n게민, 멩심허영 갓당 옵서.",
            "solution": "어느 곳으로 가십니까?\n바다에 고기 사려고 말입니다.\n왜, 누가 왔습니까?\n서울에서 작은 아버지네가 왔습니다.\n그럼, 조심해서 갔다 오십시오.",
            "soundUrl": "/media/wuz",
            "image1Url": "/media/wtb",
            "category": "ADMIN",
            "count": "1009"
        },
        {
            "seq": "25",
            "type": "LB07",
            "name": "조근게 요망진다",
            "siteName": "작은 것이 똑똑하고 영리하다",
            "contents": "족댕 나무래지 말라.\n조근게 요망진다.\n큰 건 보롬만 불어도, 홍글랑 홍글랑 호지만\n호꼴락 혼 건, 똔똔호곡 펜주룽 혼다.",
            "original": "족뎅 나무래지 말라.\n족으게 요망진다.\n큰 건 &#58954;롬만 불어도, 홍글랑홍글랑 &#62775;지만\n&#62775;꼴락 &#62778; 건, &#58253;&#58253;&#62775;곡 펜주룽&#62778;다.",
            "solution": "작다고 놀리지 마라.\n작은 것이 똑똑하고 영리하다.\n큰 것은 바람만 불어도, 흔들 흔들 거리지만\n조그만 한 건, 단단하고 태연하게 있는다.",
            "soundUrl": "/media/wul",
            "image1Url": "/media/wtv",
            "category": "ADMIN",
            "count": "1199"
        },
        {
            "seq": "24",
            "type": "LB06",
            "name": "으마떵 호리",
            "siteName": "이런, 어떻게 하나",
            "contents": "똘년이 돌으멍 가단 푸더전 마씀. \n으마떵 호리. 경 호연 어떵 해서 ?\n병원에 갔수게.\n간 보난, 꽝이 뿌서졌덴 마씀.\n혼, 열흘간 입원 해사 혼덴 햄쑤다.",
            "original": "&#58344;년이 &#58255;으멍 가단 푸더전마씀.\n어마떵 &#62775;리. 경&#62775;연 어떵 해서?\n병원에 갓수게.\n간 보난, 꽝이 뿌서젓덴마씀.\n&#62778;, 열흘간 입원헤사 &#62778;덴 햄수다.",
            "solution": "딸이 뛰어 가다가 쓰러졌답니다.\n이런, 어떻게 하나. 그래서 어떻게 했는가 ?\n병원에 갔습니다.\n가서 보니까 뼈가 부러졌답니다.\n한, 열흘간 입원 해야 한다고 합니다.",
            "soundUrl": "/media/wuk",
            "image1Url": "/media/wtc",
            "category": "ADMIN",
            "count": "1450"
        },
        {
            "seq": "23",
            "type": "LB06",
            "name": "먹돌도 똘람 시민 고망이 난다",
            "siteName": "차돌도 뚫고 있으면 구멍이 난다",
            "contents": "시험에 떨어진 아들이 아방 안티 말했수다.\n`난, 아명 해도 안되쿠다.`\n`무사, 안된댄 생각 햄시냐?`\n`해도 해도 안되는디, 어떵홉니까?`\n`먹돌도 똘람 시민 고망이 난다. 햄시민 된다.`",
            "original": "시험에 떨어진 아들이 아방안티 말헷수다.\n난, 아명헤도 안뒈쿠다.\n무사, 안 &#46220;덴 생각햄시냐?\n해도 해도 안뒈는디, 어떵&#62790;니까?\n먹돌도 &#58344;람시민 고망이 난다. 헴시민&#46220;다.",
            "solution": "시험에 떨어진 아들이 아버지께 말했습니다.\n`난, 아무리 해도 안되겠습니다.`\n`왜, 안된다고 생각하느냐?`\n`해도 해도 안되는걸, 어떻게 합니까?`\n`차돌도 뚫고 있으면 구멍이 난다. 하고 있으면 된다.`",
            "soundUrl": "/media/wuj",
            "image1Url": "/media/wtx",
            "category": "ADMIN",
            "count": "896"
        },
        {
            "seq": "22",
            "type": "LB06",
            "name": "초마 가라, 도둑놈 심뽀구나",
            "siteName": "아니 원, 그거 도둑놈 마음이구나",
            "contents": "이추룩 억울할 때가 있수과?\n소정해도 시원호지 않을 놈이 큰 소리라 마씸.\n초마 가라, 그거 도둑놈 심뽀구나.\n게메 마씸, 그런 사롬이 어디 있수과?",
            "original": "이추룩 억울할 때가 잇수과?\n&#59773;정헤도 시원&#62775;지 않을 놈이 큰 소리라마씸.\n&#62273;마가라, 그거 도둑놈 심뽀구나.\n게메마씸, 그런 사롬이 어디 잇수과?",
            "solution": "이렇게 억울할 때가 있습니까?\n사정을 해도 시원하지 않을 놈이 큰 소리 합니다.\n아니 원, 그거 도둑놈 마음이구나.\n그러게 말입니다, 그런 사람이 어디 있습니까?\n( ※ 게메 마씸 : 게메 마씀 이라고도 함)",
            "soundUrl": "/media/wuh",
            "image1Url": "/media/wtz",
            "category": "ADMIN",
            "count": "1249"
        },
        {
            "seq": "21",
            "type": "LB05",
            "name": "어드레 감디?",
            "siteName": "어디로 가느냐?",
            "contents": "어드레 감디?\n바당에 어멍 안티 감쑤다.\n경 호건, 이거 가정 가라.\n무싱 거꽈?\n느네 어멍, 바당에서 물질 호멍 먹을거여.",
            "original": "어드레 감디?\n바당에 어멍안티 감수다.\n경&#62775;건, 이거 가정 가라.\n무싱 거과?\n느네 어멍, 바당에서 물질&#62775;멍 먹을 거여.",
            "solution": "어디로 가느냐?\n바다에 어머니 한테 갑니다.\n그러면, 이거 가지고 가라.\n무엇입니까?\n너희 어머니, 바다에서 물질하면서 먹을거다.",
            "soundUrl": "/media/wug",
            "image1Url": "/media/wtl",
            "category": "ADMIN",
            "count": "1526"
        },
        {
            "seq": "20",
            "type": "LB01",
            "name": "시집살이 이야기",
            "siteName": "시집살이 이야기",
            "contents": "시집 가 보난 영 해라. \n돌탱이 고튼 시아방에,\n물폐기 고튼 시어멍에\n물꾸럭 고튼 서방에,\n고냥독새 고튼 시누이에,\n가도 가도 고생이라라.",
            "original": "시집 가 보난 영 해라.\n돌탱이 &#57767;튼 시아방에,\n물페기 &#57767;튼 시어멍에\n물꾸럭 &#57767;튼 서방에,\n&#57767;냥독새 &#57767;튼 시누이에,\n가도 가도 고생이라라.",
            "solution": "시집을 가 보니까 이렇드라.\n돌덩이 같이 고집 센 시아버지에,\n살모사 같이 독한 시어머니에,\n문어 같이 물렁물렁한 남편에,\n굴뚝새 같이 약아 빠진 시누이에,\n살아도 살아도 고생이더라.",
            "soundUrl": "/media/wuf",
            "image1Url": "/media/wtk",
            "category": "ADMIN",
            "count": "1150"
        },
        {
            "seq": "19",
            "type": "LB06",
            "name": "동 텃저, 어서 글라",
            "siteName": "날이 밝았다, 어서 가자",
            "contents": "동 텃저, 어서 글라. \n일 해사 먹엉 산다.\n부지런 혼 건 하늘도 못 막낸 해라.\n혼저 촐령 가사, 일 홀 거 아니가.",
            "original": "동 텃저, 어서 글라.\n일 헤사 먹엉 산다.\n부지런&#62778; 건 하늘도 못 막넨 해라.\n&#62778;저 &#62277;령 가사, 일 &#62780; 거 아니가.",
            "solution": "날이 밝았다, 어서 가자.\n일 해야 먹고 산다.\n부지런한 것은 하늘도 못 막는다고 하더라.\n뻘리 준비해서 가야, 일 할 것 아니냐.\n( ※ 동 텃저 : 해가 떳다)",
            "soundUrl": "/media/wud",
            "image1Url": "/media/wtj",
            "category": "ADMIN",
            "count": "926"
        },
        {
            "seq": "18",
            "type": "LB06",
            "name": "맨도롱 홀 때 호로록 들여 싸붑서",
            "siteName": "따뜻할 때 후루룩 마셔 버리십시오",
            "contents": "혼저 왕 먹읍서. \n맨도롱 했수과?\n&#46627;&#46627;혼 게 먹기 똑 좋았수다.\n맨도롱 홀 때 호로록 들여 싸붑서.",
            "original": "&#62778;저 왕 먹읍서.\n맨도롱 햇수과?\n&#58346;&#58346;&#62778; 게 먹기 똑 좋앗수다.\n맨도롱 &#62780; 때 호로록 들이싸붑서.",
            "solution": "어서 와서 먹으십시오.\n따뜻합니까?\n따끈따끈한 것이 먹기에 꼭 좋았습니다.\n따뜻할 때 후루룩(입에 넣는 모습) 마셔 버리십시오.",
            "soundUrl": "/media/wus",
            "image1Url": "/media/wth",
            "category": "ADMIN",
            "count": "1248"
        },
        {
            "seq": "17",
            "type": "LB07",
            "name": "둥그리멍 키워서 혼다",
            "siteName": "고생시키며 키워야 한다",
            "contents": "요새 아이덜, 너무 호강 햄쩌\n경 호난, 호꼼호민 아프곡, 울곡 햄시녜.\n둥구리멍 질룬 독새시가 빙애기 된댕 혼다. \n어진 때 고생도 호곡 해사 큰 사롬 된다.",
            "original": "요새 아이덜, 너미 호강 햄저.\n경&#62775;난, &#62775;꼬&#62775;민 아프곡, 울곡 햄시녜.\n둥그리멍 질룬 &#58251;새기가 빙애기 &#46220;뎅 &#62778;다.\n어릴 때 고셍도 &#62775;곡 해사 큰 사&#58487; &#46220;다.",
            "solution": "요사이 아이들, 너무 편안히 산다\n그러니까, 조금하면 아프고, 울고 하고 있다.\n뒹글리면서 기른 달걀이 병아리가 된다고 한다.\n어릴 때 고생도 하고 해야 큰 사람 된다.\n( ※ 둥구리멍 질룬 독새기 : 고생시키며 키운 달걀)",
            "soundUrl": "/media/wua",
            "image1Url": "/media/wtg",
            "category": "ADMIN",
            "count": "1766"
        },
        {
            "seq": "16",
            "type": "LB07",
            "name": "조냥 정신",
            "siteName": "절약 정신",
            "contents": "조냥 하멍 살아사 혼다.\n오늘보다 내일 생각호곡, \n내일보다 모레 생각호곡,\n경 해사 일생을 펜안호게 살아진다.",
            "original": "&#61948;냥 허멍 살아사 &#62778;다.\n오늘보다 내일 생각&#62775;곡\n내일보다 모리 생각&#62775;곡\n경헤사 일생을 펜안&#62775;게 살아진다.",
            "solution": "아끼면서 살아야 한다.\n오늘보다 내일을 생각하고,\n내일보다 모레를 생각하고,\n그렇게 해사 일생을 편히 살수 있단다.\n( ※ 조냥 : '절약'을 뜻함\n ※ 조냥정신 : 제주 선조들은 이 조냥정신으로 일생을 살아왔으며 삶의 근본이 되었읍니다.)",
            "soundUrl": "/media/wup",
            "image1Url": "/media/wtf",
            "category": "ADMIN",
            "count": "1880"
        },
        {
            "seq": "15",
            "type": "LB03",
            "name": "서귀포 바당에 강 봅서",
            "siteName": "서귀포 바다에 가서 보세요",
            "contents": "서귀포 바당에 가민 알아 짐니다. \n무신것이 소랑이고, 무신 것이 그리움인지, \n안개 낀 부둣가에 뱃고동 울어 주민, \n옛님이 그리웡 눈물이 잘도 납니다.",
            "original": "서귀포 바당에 가민 알아집니다.\n무신 것이 &#59773;랑이고, 무신 것이 그리움인지\n안개 낀 선창에 뱃고동 울어 주민,\n옛님이 그리웡 눈물이 잘도 남수다.",
            "solution": "서귀포 바다에 가면 알수 있습니다.\n무엇이 사랑이고, 무엇이 그리움인지,\n안개 낀 부둣가에 뱃고동 울어 주면,\n옛님이 그리워서 눈물이 많이도 납니다.",
            "soundUrl": "/media/wuo",
            "image1Url": "/media/wtd",
            "category": "ADMIN",
            "count": "1030"
        },
        {
            "seq": "14",
            "type": "LB07",
            "name": "욕은 고냉이 밤눈 어둡나",
            "siteName": "약은 고양이가 밤눈이 어둡다",
            "contents": "사롬은 서로 서로 도우멍 사는 거여!\n욕은 고냉이 밤눈 어둡덴 혼다.\n이녁만 욕은 체 호멍 살당 보민 \n지 욕심에 걸령 지가 넘어진다.",
            "original": "사롬은 서로 서로 도우멍 사는 거여\n욕은 고넹이 밤눈 어둡덴 &#62778;다.\n이녁만 욕은 체 &#62775;멍 살당 보민 \n지 욕심에 걸령 지가 넘어진다.",
            "solution": "사람은 서로 서로 도우며 사는 것이야!\n약은 고양이가 밤눈이 어둡다고 한다.\n자기만 약은 체 하면서 살다 보면\n자기 욕심에 걸려서 자기가 넘어진단다.",
            "soundUrl": "/media/wui",
            "image1Url": "/media/wts",
            "category": "ADMIN",
            "count": "1488"
        },
        {
            "seq": "13",
            "type": "LB07",
            "name": "인생 살이",
            "siteName": "인생 살이",
            "contents": "바다에 강 봐사, 풍랑을 알아 지곡\n조식을 나 봐사, 부모 모심 알아 지곡\n사롬은 만낭 살아 봐사, 진심을 알아 지곡\n소랑을 해 봐사, 눈물도 알아 짐니다.",
            "original": "바다에 강 봐사, 풍랑을 알아지곡\n&#61948;식을 나봐사, 부모 &#58720;심 알아지곡\n사롬은 만낭 살아봐사, 진심을 알아지곡\n&#59773;랑을 해봐사, 눈물도 알아집니다.",
            "solution": "바다에 가서 보아야, 풍랑을 알게 되고\n자식을 낳아 보아야, 부모 마음 알게 되고\n사람은 만나서 살아 보아야, 진짜 마음을 알게 되고\n사랑을 해 보아야, 눈물도 알게 된답니다.",
            "soundUrl": "/media/wuu",
            "image1Url": "/media/wta",
            "category": "ADMIN",
            "count": "1175"
        },
        {
            "seq": "12",
            "type": "LB02",
            "name": "돌고망으로 본 바당",
            "siteName": "돌구멍으로 보는 바다",
            "contents": "삼다도옌 행게마는 촘말 돌이 많쑤다. 양?\n옛날엔 한락산이 화산이란 돌이 많쑤게.\n아이고 게, 저기 돌고망에 핀 꽃 봅서\n돌고망으로 보는 바당은 꼭 그림 답쑤다.",
            "original": "삼다도옌 헹게마는 &#62283;말 돌이 하우다. 양?\n옛날엔 할락산이 화산이난 돌이 하수게.\n아이고게, 저기 돌고망에 핀 꼿 봅서\n돌고망으로 보는 바당은 꼭 그림 답쑤다.",
            "solution": "삼다도라고 하더니만 정말 돌이 많습니다. 예?\n옛날에는 한라산이 화산이었기 때문에 돌이 많답니다. \n아이고, 저기 돌구멍에 핀 꽃 보십시오.\n돌구멍으로 보는 바다는 꼭 그림 같군요.",
            "soundUrl": "/media/wuy",
            "image1Url": "/media/wtp",
            "category": "ADMIN",
            "count": "1231"
        },
        {
            "seq": "11",
            "type": "LB07",
            "name": "무사 경 고람쑤꽈?",
            "siteName": "왜 그렇게 말하십니까?",
            "contents": "무사 경 고람쑤과?\n혼저 왕 소랑하멍 살게 마씀.\n성 내멍 살아도 혼 세상\n저들멍 살아도 혼 세상 이우다.\n가난해서 웃으멍 살게 마씀.",
            "original": "무사 경 &#57773;암수과?\n&#62778;저 왕 &#59773;랑허멍 살게마씀.\n성 내멍 살아도 &#62778; 세상\n저들멍 살아도 &#62778; 세상이우다.\n가난헤도 웃으멍 살게마씀.",
            "solution": "왜 그렇게 말하십니까?\n어서 와서 사랑하면서 살아 봅시다. \n화를 내면서 살아도 한 세상\n걱정하면서 살아도 한 세상 입니다.\n가난해도 웃으면서 살아 봅시다.",
            "soundUrl": "/media/wut",
            "image1Url": "/media/wto",
            "category": "ADMIN",
            "count": "1408"
        },
        {
            "seq": "10",
            "type": "LB01",
            "name": "신랑 신부 이야기 ③",
            "siteName": "신랑 신부 이야기 ③",
            "contents": "신랑이 신부에게 말했수게.\n`이 조끄뜨레 오라게.`\n`무사 조끄뜨레만 오랜 햄수과?`\n`호꼼이라도 고치만 있고 싶언.`\n`놈덜 웃읍니다.`\n`어떵 호느냐? 소랑에는 부치룸이 엇나.`",
            "original": "신랑이 신부신디 말헷수게.\n이 &#61948;꼇듸 오라게.\n무사 &#61948;꼇듸레 오렌 햄수과?\n&#62775;꼼이라도 &#57767;치만 잇고 싶언.\n놈덜 웃읍니다.\n어떵 &#62775;느냐? &#59773;랑에는 부치럼이 엇나.",
            "solution": "신랑이 신부에게 말했답니다.\n`여기 가까이(옆에) 오너라.`\n`왜 가까이(옆에)만 오라고 하십니까?`\n`조금이라도 같이만 있고 싶어서.`\n`남들이 웃습니다.`\n`어떡하느냐? 사랑에는 부끄러움이 없단다.`",
            "soundUrl": "/media/wur",
            "image1Url": "/media/wti",
            "category": "ADMIN",
            "count": "1879"
        },
        {
            "seq": "9",
            "type": "LB01",
            "name": "신랑 신부 이야기 ②",
            "siteName": "신랑 신부 이야기 ②",
            "contents": "새 각시가 새 서방 품에서 솔째기 말해십주.\n`날 얼마나 소랑햄쑤과?`\n`저기 한락산만큼, 또 바당만큼 소랑햄쩌.`\n`경 마랑, 요 가슴패기 만큼만 소랑해 줍서.`\n`기여, 느영 나영 두리 둥실 소랑호게.`",
            "original": "새각시가 새시방 품에서 &#59778;째기 말헤십주\n날 얼마나 &#59773;랑헴수과?\n저기 할락산만큼, 또 바당만큼 &#59773;랑헴저.\n경 말앙, 요 가슴페기만큼만 &#59773;랑해 줍서.\n기여, 느영 나영 두리둥실 &#59773;랑호게.",
            "solution": "신부가 신랑 품에서 살그머니 말했답니다.\n`나를 얼마나 사랑하십니까?`\n`저기 한라산만큼, 또 바다만큼 사랑한다.`\n`그러지 말고 이 가슴팍 만큼만 사랑해 주십시오.`\n`그래, 너하고 나하고 둘이 둥실 사랑하자.`",
            "soundUrl": "/media/wue",
            "image1Url": "/media/wtu",
            "category": "ADMIN",
            "count": "1470"
        },
        {
            "seq": "8",
            "type": "LB01",
            "name": "신랑 신부 이야기 ①",
            "siteName": "신랑 신부 이야기 ①",
            "contents": "장게간 날 밤, 새 서방이 말했수게.\n`새 각시야, 혼저 오라게.`\n`무사 마씀?`\n`호꼼만 이십서게.`\n`뭉캐지 말앙 혼저 오라게.`",
            "original": "장게간 날 밤, 새시방이 말햇수게.\n새각시야, &#62778;저 오라게.\n무사 마씀?\n&#62775;꼼만 이십서게.\n&#58739;케지 말앙 &#62778;저 오라게.",
            "solution": "장가간 날 밤, 새 신랑이 말했습니다.\n`색씨야, 어서 오너라.`\n`왜 그러십니까?`\n`조금만 계십시오.`\n`꾸물대지 말고 어서 오너라.`",
            "soundUrl": "/media/wuw",
            "image1Url": "/media/wty",
            "category": "ADMIN",
            "count": "1550"
        },
        {
            "seq": "7",
            "type": "LB07",
            "name": "돌 하르방 손지들",
            "siteName": "돌하르방 손자들",
            "contents": "제주 사롬들은 돌 하르방 보멍 살았수다. \n경 호난, 거짓말 홀 줄 모르곡\n서로 믿으멍 착하게만 살았수게.\n봅서, 어시민 도와 주곡, 이시민 나누엉 먹곡,\n인정 많고, 소랑 많은 돌하르방 손지들 이우다.",
            "original": "제주 사&#58487;들은 돌하르방 보멍 살앗수다.\n경&#62775;난, 거짓말 &#62780; 줄 몰르곡\n서로 믿으멍 착&#62775;게만 살앗수게\n봅서, 어시민 도와 주곡, 이시민 나&#45481; 먹곡,\n인정 많고, &#59773;랑 많은 돌하르방 손지들 이우다.",
            "solution": "제주 사람들은 돌 하르방 보면서 살았습니다.\n그러니까, 거짓말 할 줄 모르고\n서로 믿으면서 착하게만 살았습니다.\n보십시오, 없으면 도와 주고, 있으면 나누어서 먹으면서,\n인정 많고, 사랑이 많은 돌하르방 손자들 입니다.",
            "soundUrl": "/media/wuq",
            "image1Url": "/media/wtt",
            "category": "ADMIN",
            "count": "1341"
        },
        {
            "seq": "6",
            "type": "LB02",
            "name": "한라산에 올랑 봅서",
            "siteName": "한라산에 올라서 보십시오",
            "contents": "한락산에 올랑 봅서. \n발 아래 구름들이 왔닥갔닥 호곡\n아득혼게 꿈속 고틉니다.\n옛날에 신선들이 힌 사슴 타멍\n놀았댄 해연 백록담 아니꽈.",
            "original": "할락산에 올랑 봅서.\n발 아래 구름들이 왓닥갓닥 &#62775;곡\n아득&#62778;게 꿈속 &#57767;트우다.\n옛날에 신선들이 흰 사슴 타멍\n놀앗덴 &#62775;연 백록담 아니우과",
            "solution": "한라산에 올라서 보십시오. \n발 아래 구름들이 오락가락 하고\n아듣하니 꿈속 같습니다.\n옛날에 신선들이 흰 사슴을 타며\n놀았다고 해서 백록담 아닙니까.",
            "soundUrl": "/media/wyM",
            "image1Url": "/media/wtr",
            "category": "ADMIN",
            "count": "1232"
        },
        {
            "seq": "5",
            "type": "LB03",
            "name": "제주도 보름들",
            "siteName": "제주도 바람",
            "contents": "제주도엔 보름이 많이 있수다.\n동쪽에서 부는 보름, 샛보름.\n서쪽에서 부는 보름, 갈보름\n남쪽에서 부는 보름, 마포름.\n북쪽에서 부는 보름, 하늬보름 이우다.",
            "original": "제주도엔 &#58954;름이 하영 잇수다.\n동쪽에서 부는 &#58954;름, 셋&#58954;름.\n서쪽에서 부는 &#58954;름, 갈&#58954;름\n남쪽에서 부는 &#58954;름, 마&#62606;름.\n북쪽에서 부는 &#58954;름, 하늬&#58954;름이우다.",
            "solution": "제주도에는 바람이 많이 있습니다.\n동쪽에서 부는 바람, 샛바람.\n서쪽에서 부는 바람, 갈바람.\n남쪽에서 부는 바람, 마파람.\n북쪽에서 부는 바람, 하늬바람 입니다.",
            "soundUrl": "/media/wyN",
            "image1Url": "/media/wte",
            "category": "ADMIN",
            "count": "2184"
        },
        {
            "seq": "4",
            "type": "LB02",
            "name": "왕 봅서",
            "siteName": "와서 보세요",
            "contents": "고랑은 몰라 마씀.\n제주도에 왕 봐사 알아짐니다. \n돌도 많고, 보롬도 많고, 비바리도 많고,\n유채꽃도 곱드락 호게 피었수다.\n아명 고라도 몰라 마씀. 혼저 왕 봅서.",
            "original": "&#57773;앙은 몰라마씀.\n제주도에 왕 봐사 알아집니다. \n돌도 하고, &#58954;롬도 하고, 비바리도 하고, \n유채꼿도 곱들락 &#62775;게 피엇수다.\n아명 &#57773;아도 몰라마씀. &#62778;저 왕 봅서.",
            "solution": "말로 해서는 모릅니다.\n제주도에 와서 보아야 알 수 있습니다. \n돌도 많고, 바람도 많고, 처녀도 많고,\n유채꽃도 아름답게 피었습니다.\n아무리 말해도 모릅니다. 어서 와서 보십시오.",
            "soundUrl": "/media/wyB",
            "image1Url": "/media/wtw",
            "category": "ADMIN",
            "count": "1372"
        },
        {
            "seq": "3",
            "type": "LB02",
            "name": "제주 비바리",
            "siteName": "제주 처녀",
            "contents": "저기, 물허벅 정 가는 거, 비바리덜 아니꽈?\n맞수다. 비바리도 있고, 넹바리도 있수다. \n비바리덜 곱들락 호고 놀씬하우다 양!\n경 합주게, 산 좋고 물 좋은 제주도에 사난\n모심도 착하고 얼굴도 곱들락 홉니다.",
            "original": "저기 물허벅 정 가는 거 비바리덜 아니우과?\n맞수다. 비바리도 잇고, 넹바리도 잇수다. \n비바리덜 곱들락&#62775;고 &#57992;씬허우다양!\n경헙주게, 산 좋고 물 좋은 제주도에 사난\n&#58720;심도 착허고 얼굴도 곱들락헙니다.",
            "solution": "저기, 물허벅(바구니) 지고 가는 거, 처녀들 아닙니까?\n맞습니다. 처녀도 있고, 시집 간 여자도 있습니다. \n처녀들 곱고 날씬하군요!\n그렇지요, 산 좋고 물 좋은 제주도에 사니\n마음도 착하고 얼굴도 곱습니다.\n( ※곱들락 : 동그스름하고 이쁜 모습 )",
            "soundUrl": "/media/wyV",
            "image1Url": "/media/wtq",
            "category": "ADMIN",
            "count": "1559"
        },
        {
            "seq": "2",
            "type": "LB02",
            "name": "제주도 인사",
            "siteName": "제주도 인사",
            "contents": "펜안 하우꽈? 제주도에 오난 어떵 하우꽈?\n촘말로 좋수다. 공기도 맑고,\n산이영 바당이영 몬딱 좋은게 마씀.\n서울에 갈 때랑 하영 담앙 갑서.\n게메, 양. 경 해시민 얼마나 좋코 마씀?",
            "original": "펜안허우과? 제주도에 오난 어떵허우과?\n&#62283;말로 좋수다. 공기도 맑고,\n산이영 바당이영 몬딱 좋은게마씀.\n서울에 갈 때랑 하영 담앙 갑서.\n게메양. 경 헤시민 얼마나 좋고 마씀?",
            "solution": "편안(안녕)하십니까? 제주도에 오니 어떠하십니까?\n정말로 좋습니다. 공기도 맑고,\n산이랑 바다랑 모두가 좋습니다.\n서울에 갈 때는 많이 담아서 가십시오.\n그러게 말입니다. 그렇게 했으면 얼마나 좋겠습니까?",
            "soundUrl": "/media/wyC",
            "image1Url": "/media/wrM",
            "category": "ADMIN",
            "count": "4410"
        },
        {
            "seq": "1",
            "type": "LB05",
            "name": "혼저 옵서",
            "siteName": "어서 오십시오",
            "contents": "혼저 옵서. 제주도 사투리로 말 호난,\n무신 거옌 고람 신디 몰르쿠게?\n게메 마씀, 귀 눈이 왁왁하우다.\n경해도 고만히 생각호멍 들으민 조금씩 알아집니다.\n제주도 사투리 촘말로 귀하고 아름다운 보물이우다.",
            "original": "&#62778;저 옵서. 제주도 사투리로 말&#62775;난,\n무신 거옌 &#57773;암 신디 몰르쿠게?\n게메마씀, 귀 눈이 왁왁&#62775;우다.\n경헤도 &#57767;만히 생각&#62775;멍 들으민 조금씩 알아집니다.\n제주도 사투리 &#62283;말로 귀허고 아름다운 보물이우다.",
            "solution": "어서 오십시오. 제주도 사투리로 말 하니까,\n뭐라고 말하는 지 모르겠지요?\n글쎄 말입니다. 귀와 눈이 캄캄합니다.\n그래도 가만히 생각하며 들으면 조금씩 알게됩니다.\n제주도 사투리 정말로 귀하고 아름다운 보물입니다.",
            "soundUrl": "/media/wyX",
            "image1Url": "/media/wrN",
            "category": "ADMIN",
            "count": "3035"
        }
    ]
}
